Workbook

Sheet Summary
A1: Gym CRM full regression
A2: AI: keyless stand-in (drafts and readiness from a heuristic, not a model)
A3: Generated 2026-10-16 from the agent run against http://localhost:3410 (Gym CRM (fitness-crm sample, demo data)).
A4: Yellow cells on the module sheets are for testers: Tester result (Pass, Fail, Blocked, Not run), notes and date.
A6: Module | B6: Sheet | C6: Cases | D6: Automated | E6: Manual | F6: Not drafted | G6: Agent: passed (run 2) | H6: Agent: failed (run 2) | I6: Agent: inconclusive (run 2) | J6: Tester: pass | K6: Tester: fail | L6: Tester: blocked
A7: Sign-in, sessions, roles and permissions | B7: Access | C7: =COUNTA(Access!A:A)-1 -> 79 | D7: =COUNTIF(Access!J:J,"Automated") -> 70 | E7: =COUNTIF(Access!J:J,"Manual") -> 9 | F7: =COUNTIF(Access!J:J,"Not drafted") -> 0 | G7: =COUNTIF(Access!M:M,"PASSED") -> 70 | H7: =COUNTIF(Access!M:M,"FAILED") -> 0 | I7: =COUNTIF(Access!M:M,"INCONCLUSIVE") -> 0 | J7: =COUNTIF(Access!O:O,"Pass") -> 0 | K7: =COUNTIF(Access!O:O,"Fail") -> 0 | L7: =COUNTIF(Access!O:O,"Blocked") -> 0
A8: Leads and consulting | B8: Leads | C8: =COUNTA(Leads!A:A)-1 -> 43 | D8: =COUNTIF(Leads!J:J,"Automated") -> 27 | E8: =COUNTIF(Leads!J:J,"Manual") -> 16 | F8: =COUNTIF(Leads!J:J,"Not drafted") -> 0 | G8: =COUNTIF(Leads!M:M,"PASSED") -> 27 | H8: =COUNTIF(Leads!M:M,"FAILED") -> 0 | I8: =COUNTIF(Leads!M:M,"INCONCLUSIVE") -> 0 | J8: =COUNTIF(Leads!O:O,"Pass") -> 0 | K8: =COUNTIF(Leads!O:O,"Fail") -> 0 | L8: =COUNTIF(Leads!O:O,"Blocked") -> 0
A9: Customers and contracts | B9: Customers & contracts | C9: =COUNTA('Customers & contracts'!A:A)-1 -> 45 | D9: =COUNTIF('Customers & contracts'!J:J,"Automated") -> 23 | E9: =COUNTIF('Customers & contracts'!J:J,"Manual") -> 22 | F9: =COUNTIF('Customers & contracts'!J:J,"Not drafted") -> 0 | G9: =COUNTIF('Customers & contracts'!M:M,"PASSED") -> 22 | H9: =COUNTIF('Customers & contracts'!M:M,"FAILED") -> 1 | I9: =COUNTIF('Customers & contracts'!M:M,"INCONCLUSIVE") -> 0 | J9: =COUNTIF('Customers & contracts'!O:O,"Pass") -> 0 | K9: =COUNTIF('Customers & contracts'!O:O,"Fail") -> 0 | L9: =COUNTIF('Customers & contracts'!O:O,"Blocked") -> 0
A10: PT booking, sessions, classes and check-in | B10: Booking & sessions | C10: =COUNTA('Booking & sessions'!A:A)-1 -> 36 | D10: =COUNTIF('Booking & sessions'!J:J,"Automated") -> 1 | E10: =COUNTIF('Booking & sessions'!J:J,"Manual") -> 35 | F10: =COUNTIF('Booking & sessions'!J:J,"Not drafted") -> 0 | G10: =COUNTIF('Booking & sessions'!M:M,"PASSED") -> 1 | H10: =COUNTIF('Booking & sessions'!M:M,"FAILED") -> 0 | I10: =COUNTIF('Booking & sessions'!M:M,"INCONCLUSIVE") -> 0 | J10: =COUNTIF('Booking & sessions'!O:O,"Pass") -> 0 | K10: =COUNTIF('Booking & sessions'!O:O,"Fail") -> 0 | L10: =COUNTIF('Booking & sessions'!O:O,"Blocked") -> 0
A11: Money, approvals, configuration, tasks, workouts, reports and security | B11: Operations | C11: =COUNTA(Operations!A:A)-1 -> 58 | D11: =COUNTIF(Operations!J:J,"Automated") -> 9 | E11: =COUNTIF(Operations!J:J,"Manual") -> 47 | F11: =COUNTIF(Operations!J:J,"Not drafted") -> 2 | G11: =COUNTIF(Operations!M:M,"PASSED") -> 8 | H11: =COUNTIF(Operations!M:M,"FAILED") -> 0 | I11: =COUNTIF(Operations!M:M,"INCONCLUSIVE") -> 1 | J11: =COUNTIF(Operations!O:O,"Pass") -> 0 | K11: =COUNTIF(Operations!O:O,"Fail") -> 0 | L11: =COUNTIF(Operations!O:O,"Blocked") -> 0
A12: Total | C12: =SUM(C7:C11) -> 261 | D12: =SUM(D7:D11) -> 130 | E12: =SUM(E7:E11) -> 129 | F12: =SUM(F7:F11) -> 2 | G12: =SUM(G7:G11) -> 128 | H12: =SUM(H7:H11) -> 1 | I12: =SUM(I7:I11) -> 1 | J12: =SUM(J7:J11) -> 0 | ... L12: =SUM(L7:L11) -> 0
A13: Automation coverage | C13: =IF(C12=0,0,D12/C12) -> 0.49808429
A15: Technique | B15: Cases
A16: Boundary value analysis | B16: =COUNTIF(Access!C:C,"Boundary value analysis")+COUNTIF(Leads!C:C,"Boundary value analysis")+COUNTIF('Customers & contracts'!C:C,"Boundary value analysis")+COUNTIF('Booking & sessions'!C:C,"Boundary value analysis")+COUNTIF(Operations!C:C,"Boundary value analysis") -> 35
A17: Decision table | B17: =COUNTIF(Access!C:C,"Decision table")+COUNTIF(Leads!C:C,"Decision table")+COUNTIF('Customers & contracts'!C:C,"Decision table")+COUNTIF('Booking & sessions'!C:C,"Decision table")+COUNTIF(Operations!C:C,"Decision table") -> 28
A18: Equivalence partitioning | B18: =COUNTIF(Access!C:C,"Equivalence partitioning")+COUNTIF(Leads!C:C,"Equivalence partitioning")+COUNTIF('Customers & contracts'!C:C,"Equivalence partitioning")+COUNTIF('Booking & sessions'!C:C,"Equivalence partitioning")+COUNTIF(Operations!C:C,"Equivalence partitioning") -> 34
A19: Error guessing | B19: =COUNTIF(Access!C:C,"Error guessing")+COUNTIF(Leads!C:C,"Error guessing")+COUNTIF('Customers & contracts'!C:C,"Error guessing")+COUNTIF('Booking & sessions'!C:C,"Error guessing")+COUNTIF(Operations!C:C,"Error guessing") -> 21
A20: Permission matrix | B20: =COUNTIF(Access!C:C,"Permission matrix")+COUNTIF(Leads!C:C,"Permission matrix")+COUNTIF('Customers & contracts'!C:C,"Permission matrix")+COUNTIF('Booking & sessions'!C:C,"Permission matrix")+COUNTIF(Operations!C:C,"Permission matrix") -> 77
A21: State transition | B21: =COUNTIF(Access!C:C,"State transition")+COUNTIF(Leads!C:C,"State transition")+COUNTIF('Customers & contracts'!C:C,"State transition")+COUNTIF('Booking & sessions'!C:C,"State transition")+COUNTIF(Operations!C:C,"State transition") -> 20
A22: Use case | B22: =COUNTIF(Access!C:C,"Use case")+COUNTIF(Leads!C:C,"Use case")+COUNTIF('Customers & contracts'!C:C,"Use case")+COUNTIF('Booking & sessions'!C:C,"Use case")+COUNTIF(Operations!C:C,"Use case") -> 46

Sheet Access
A1: ID | B1: Section | C1: Technique | D1: Priority | E1: Title | F1: Requirement ID | G1: Requirement | H1: Preconditions | I1: Steps (action → expected) | J1: Type | K1: Why manual | L1: Agent run 1 | M1: Agent run 2 | N1: Observed on failure | O1: Tester result | P1: Tester notes | Q1: Tested on
A2: AUTH-01 | B2: Sign-in and sessions | C2: Use case | D2: P1 | E2: A manager signs in with email and password and reaches the dashboard | F2: BR-107 | G2: A user with valid credentials signs in with email and password and lands on the dashboard "Tổng quan". | H2: Demo manager account | I2: 1. Sign in as the manager → The dashboard "Tổng quan" opens | J2: Automated | L2: PASSED | M2: PASSED
A3: AUTH-02 | B3: Sign-in and sessions | C3: Equivalence partitioning | D3: P1 | E3: A wrong password is refused with one generic message | F3: BR-107 | G3: A wrong password is refused with "The email or password is wrong, or the account is disabled." and the user stays on /login. | H3: Demo manager account | I3: 1. Sign in as the manager with a wrong password → The generic message is shown; still on /login | J3: Automated | L3: PASSED | M3: PASSED
A4: AUTH-03 | B4: Sign-in and sessions | C4: Error guessing | D4: P1 | E4: An unknown email gets the same message as a wrong password (no account discovery) | F4: BR-107 | G4: Signing in with an email that has no account shows the same "The email or password is wrong, or the account is disabled." message. | H4: No account for nobody@fitness-crm.test | I4: 1. Sign in as nobody@fitness-crm.test → The same generic message; nothing reveals whether the account exists | J4: Automated | L4: PASSED | M4: PASSED
A5: AUTH-04 | B5: Sign-in and sessions | C5: State transition | D5: P1 | E5: A signed-out visitor who opens the dashboard is sent to the login page | F5: AC-01 | G5: A visitor who is not signed in and opens /dashboard by direct URL is sent to /login. | H5: Not signed in | I5: 1. Open /dashboard → The login page opens | J5: Automated | L5: PASSED | M5: PASSED
A6: AUTH-05 | B6: Sign-in and sessions | C6: Equivalence partitioning | D6: P2 | E6: A signed-out deep link to a record page is sent to the login page | F6: AC-01 | G6: A visitor who is not signed in and opens /contracts by direct URL is sent to /login. | H6: Not signed in | I6: 1. Open /contracts → The login page opens | J6: Automated | L6: PASSED | M6: PASSED
A7: AUTH-06 | B7: Sign-in and sessions | C7: State transition | D7: P1 | E7: After signing out, the dashboard needs a new sign-in | F7: BR-107 | G7: After "Đăng xuất" from the account menu, opening /dashboard sends the user to /login. | H7: Signed in as the manager | I7: 1. Account menu "Tài khoản" > "Đăng xuất" → The login page opens 2. Open /dashboard → Sent to /login again | J7: Automated | L7: PASSED | M7: PASSED
A8: AUTH-07 | B8: Sign-in and sessions | C8: Decision table | D8: P2 | E8: Sign-in outside the allowed hours or days is refused | F8: BR-107 | G8: Accounts can sign in only within their allowed hours and days. | H8: A user whose allowed hours exclude the current time | I8: 1. Sign in outside the allowed window → Sign-in refused; the attempt is in the login history as failed 2. Sign in inside the window → Signed in | J8: Manual | K8: Depends on time passing (timers, reminders, expiry); needs a controllable clock.
A9: AUTH-08 | B9: Sign-in and sessions | C9: Equivalence partitioning | D9: P2 | E9: A disabled account cannot sign in and gets the generic message | F9: BR-107 | G9: A disabled account is refused with the generic sign-in message. | H9: Admin disables a test user | I9: 1. Sign in as the disabled user → "The email or password is wrong, or the account is disabled." | J9: Manual | K9: Needs two people acting in sequence (submit, then approve as someone else) inside one test.
A10: AUTH-09 | B10: Sign-in and sessions | C10: Use case | D10: P2 | E10: Every sign-in attempt is recorded with device and IP | F10: BR-107 | G10: Sign-ins are recorded with device and IP in the login history. | H10: Admin can open Users > a user > Login history | I10: 1. Sign in once with a wrong and once with the right password → Both attempts appear with result, device and IP | J10: Manual | K10: Needs two people acting in sequence (submit, then approve as someone else) inside one test.
A11: AUTH-10 | B11: Sign-in and sessions | C11: Boundary value analysis | D11: P2 | E11: Sign-in is rate limited at 20 attempts per minute per IP | F11: BR-107 | G11: The sign-in endpoint allows 20 attempts per 60 seconds per IP; the 21st is refused. | H11: A clean rate-limit window | I11: 1. Make 20 sign-in attempts within a minute → All are processed 2. Make the 21st → Refused with HTTP 429 3. Wait for the window to pass → Sign-in works again | J11: Manual | K11: Depends on time passing (timers, reminders, expiry); needs a controllable clock.
A12: AUTH-11 | B12: Sign-in and sessions | C12: Boundary value analysis | D12: P3 | E12: A session ends after 12 hours without activity | F12: BR-107 | G12: A session lasts one working day (12 hours) without activity. | H12: Signed in | I12: 1. Stay inactive for just under 12 hours → Still signed in 2. Stay inactive for 12 hours → "Phiên đăng nhập đã hết. Hãy đăng nhập lại." | J12: Manual | K12: Depends on time passing (timers, reminders, expiry); needs a controllable clock.
A13: RBAC-01A | B13: Roles and permissions | C13: Permission matrix | D13: P1 | E13: Admin can open /admin/users | F13: AC-01 | G13: Users, roles, permissions: Admin only: Admin opens /admin/users ("Người dùng"); Fitness Manager sees "Bạn không có quyền xem trang này". | H13: Demo Admin account | I13: 1. Sign in as Admin and open /admin/users → The page "Người dùng" opens | J13: Automated | L13: PASSED | M13: PASSED
A14: RBAC-01B | B14: Roles and permissions | C14: Permission matrix | D14: P1 | E14: Fitness Manager cannot open /admin/users | F14: AC-01 | G14: Users, roles, permissions: Admin only: Admin opens /admin/users ("Người dùng"); Fitness Manager sees "Bạn không có quyền xem trang này". | H14: Demo Fitness Manager account | I14: 1. Sign in as Fitness Manager and open /admin/users directly → "Bạn không có quyền xem trang này" | J14: Automated | L14: PASSED | M14: PASSED
A15: RBAC-02A | B15: Roles and permissions | C15: Permission matrix | D15: P1 | E15: Admin can open /admin/roles | F15: AC-01 | G15: Users, roles, permissions: Admin only: Admin opens /admin/roles ("Vai trò và phân quyền"); Fitness Manager sees "Bạn không có quyền xem trang này". | H15: Demo Admin account | I15: 1. Sign in as Admin and open /admin/roles → The page "Vai trò và phân quyền" opens | J15: Automated | L15: PASSED | M15: PASSED
A16: RBAC-02B | B16: Roles and permissions | C16: Permission matrix | D16: P1 | E16: Fitness Manager cannot open /admin/roles | F16: AC-01 | G16: Users, roles, permissions: Admin only: Admin opens /admin/roles ("Vai trò và phân quyền"); Fitness Manager sees "Bạn không có quyền xem trang này". | H16: Demo Fitness Manager account | I16: 1. Sign in as Fitness Manager and open /admin/roles directly → "Bạn không có quyền xem trang này" | J16: Automated | L16: PASSED | M16: PASSED
A17: RBAC-03A | B17: Roles and permissions | C17: Permission matrix | D17: P1 | E17: Admin can open /admin/options | F17: AC-01 | G17: Configuration: Admin only: Admin opens /admin/options ("Danh mục lựa chọn"); Fitness Manager sees "Bạn không có quyền xem trang này". | H17: Demo Admin account | I17: 1. Sign in as Admin and open /admin/options → The page "Danh mục lựa chọn" opens | J17: Automated | L17: PASSED | M17: PASSED
A18: RBAC-03B | B18: Roles and permissions | C18: Permission matrix | D18: P1 | E18: Fitness Manager cannot open /admin/options | F18: AC-01 | G18: Configuration: Admin only: Admin opens /admin/options ("Danh mục lựa chọn"); Fitness Manager sees "Bạn không có quyền xem trang này". | H18: Demo Fitness Manager account | I18: 1. Sign in as Fitness Manager and open /admin/options directly → "Bạn không có quyền xem trang này" | J18: Automated | L18: PASSED | M18: PASSED
A19: RBAC-04A | B19: Roles and permissions | C19: Permission matrix | D19: P1 | E19: Admin can open /admin/parameters | F19: AC-01 | G19: Configuration: Admin only: Admin opens /admin/parameters ("Tham số hệ thống"); Fitness Manager sees "Bạn không có quyền xem trang này". | H19: Demo Admin account | I19: 1. Sign in as Admin and open /admin/parameters → The page "Tham số hệ thống" opens | J19: Automated | L19: PASSED | M19: PASSED
A20: RBAC-04B | B20: Roles and permissions | C20: Permission matrix | D20: P1 | E20: Fitness Manager cannot open /admin/parameters | F20: AC-01 | G20: Configuration: Admin only: Admin opens /admin/parameters ("Tham số hệ thống"); Fitness Manager sees "Bạn không có quyền xem trang này". | H20: Demo Fitness Manager account | I20: 1. Sign in as Fitness Manager and open /admin/parameters directly → "Bạn không có quyền xem trang này" | J20: Automated | L20: PASSED | M20: PASSED
A21: RBAC-05A | B21: Roles and permissions | C21: Permission matrix | D21: P1 | E21: Admin can open /admin/trash | F21: AC-01 | G21: Trash: view, Admin only (AC-13): Admin opens /admin/trash ("Thùng rác"); Fitness Manager sees "Bạn không có quyền xem trang này". | H21: Demo Admin account | I21: 1. Sign in as Admin and open /admin/trash → The page "Thùng rác" opens | J21: Automated | L21: PASSED | M21: PASSED
A22: RBAC-05B | B22: Roles and permissions | C22: Permission matrix | D22: P1 | E22: Fitness Manager cannot open /admin/trash | F22: AC-01 | G22: Trash: view, Admin only (AC-13): Admin opens /admin/trash ("Thùng rác"); Fitness Manager sees "Bạn không có quyền xem trang này". | H22: Demo Fitness Manager account | I22: 1. Sign in as Fitness Manager and open /admin/trash directly → "Bạn không có quyền xem trang này" | J22: Automated | L22: PASSED | M22: PASSED
A23: RBAC-06A | B23: Roles and permissions | C23: Permission matrix | D23: P1 | E23: Admin can open /admin/audit | F23: AC-01 | G23: History: audit.view, Admin only: Admin opens /admin/audit ("Lịch sử thao tác"); Fitness Manager sees "Bạn không có quyền xem trang này". | H23: Demo Admin account | I23: 1. Sign in as Admin and open /admin/audit → The page "Lịch sử thao tác" opens | J23: Automated | L23: PASSED | M23: PASSED
A24: RBAC-06B | B24: Roles and permissions | C24: Permission matrix | D24: P1 | E24: Fitness Manager cannot open /admin/audit | F24: AC-01 | G24: History: audit.view, Admin only: Admin opens /admin/audit ("Lịch sử thao tác"); Fitness Manager sees "Bạn không có quyền xem trang này". | H24: Demo Fitness Manager account | I24: 1. Sign in as Fitness Manager and open /admin/audit directly → "Bạn không có quyền xem trang này" | J24: Automated | L24: PASSED | M24: PASSED
... A76: RBAC-M4 | B76: Roles and permissions | C76: Permission matrix | D76: P3 | E76: An admin can add a service | F76: AC-01 | G76: An Admin sees the "Thêm dịch vụ" action on Services. | H76: Admin account | I76: 1. Open Services as Admin → "Thêm dịch vụ" is offered | J76: Automated | L76: PASSED | M76: PASSED
A77: RBAC-M5 | B77: Roles and permissions | C77: Permission matrix | D77: P1 | E77: A consultant sees only their own leads and customers | F77: BR-101 | G77: Data scope "own": a consultant sees leads added by them or in their charge; another consultant's lead says who has it, with no way in. | H77: Two consultants, each with a lead | I77: 1. Sign in as consultant A; open the lead list → Only A's leads 2. Open consultant B's lead by URL → Shows who has it, with no way in | J77: Manual | K77: Needs data the demo seed does not have; prepared by hand or by an API fixture first.
A78: RBAC-M6 | B78: Roles and permissions | C78: Permission matrix | D78: P1 | E78: A role with phone numbers hidden never sees them, on screen or in exports | F78: AC-01 | G78: A role with phone numbers hidden never sees them on any screen or export. | H78: A role with the customer phone field hidden (e.g. Marketing) | I78: 1. Open customers and a customer as that role → No phone numbers 2. Export the list → The file has no phone column | J78: Manual | K78: Needs data the demo seed does not have; prepared by hand or by an API fixture first.
A79: RBAC-M7 | B79: Roles and permissions | C79: Permission matrix | D79: P2 | E79: A per-user override switches one permission off | F79: FR-PLT-003 | G79: Admin switches individual permissions on or off per user; the change applies immediately. | H79: Admin and a receptionist | I79: 1. Admin removes payment.view from the receptionist → The receptionist's /finance/payments is refused at the next page load | J79: Manual | K79: Needs two people acting in sequence (submit, then approve as someone else) inside one test.
A80: RBAC-M8 | B80: Roles and permissions | C80: Permission matrix | D80: P2 | E80: A user sees only the branches granted to them | F80: BR-101 | G80: Every business record belongs to a branch; a user sees and acts only in the branches granted to them. | H80: Two branches with data; a user granted one | I80: 1. Open lists as that user → Only the granted branch's records | J80: Manual | K80: Needs data the demo seed does not have; prepared by hand or by an API fixture first.

Sheet Leads
A1: ID | B1: Section | C1: Technique | D1: Priority | E1: Title | F1: Requirement ID | G1: Requirement | H1: Preconditions | I1: Steps (action → expected) | J1: Type | K1: Why manual | L1: Agent run 1 | M1: Agent run 2 | N1: Observed on failure | O1: Tester result | P1: Tester notes | Q1: Tested on
A2: LEAD-01 | B2: Leads and consulting | C2: Use case | D2: P1 | E2: A lead is saved with only a name and a channel | F2: AC-25 | G2: A lead needs only a name and a channel: name "QA LEAD-01" and channel "Zalo" save and open the new lead. | H2: Signed in as the manager | I2: 1. Leads > "Thêm lead": name and channel Zalo only; save → The new lead page opens with its name | J2: Automated | L2: PASSED | M2: PASSED
A3: LEAD-02 | B3: Leads and consulting | C3: Equivalence partitioning | D3: P1 | E3: An empty name is refused | F3: AC-25 | G3: Saving a lead with a channel but no name shows "Bắt buộc nhập." and saves nothing. | I3: 1. Choose channel Zalo, leave the name empty; save → "Bắt buộc nhập."; the dialog stays open | J3: Automated | L3: PASSED | M3: PASSED
A4: LEAD-03 | B4: Leads and consulting | C4: Error guessing | D4: P2 | E4: A name of spaces only is refused | F4: AC-25 | G4: A lead name of spaces only counts as empty: "Bắt buộc nhập." | I4: 1. Name " ", channel Zalo; save → "Bắt buộc nhập." | J4: Automated | L4: PASSED | M4: PASSED
A5: LEAD-04 | B5: Leads and consulting | C5: Boundary value analysis | D5: P2 | E5: A one-character name is accepted (minimum) | F5: AC-25 | G5: A lead name of 1 character is accepted (the name is 1 to 150 characters). | I5: 1. Name "Q", channel Zalo; save → The lead "Q" is saved and opens | J5: Automated | L5: PASSED | M5: PASSED
A6: LEAD-05 | B6: Leads and consulting | C6: Boundary value analysis | D6: P2 | E6: A 150-character name is accepted (maximum) | F6: AC-25 | G6: A lead name of 150 characters is accepted; 151 is "Quá dài." | I6: 1. Name of 150 characters, channel Zalo; save → Saved; no "Quá dài." | J6: Automated | L6: PASSED | M6: PASSED
A7: LEAD-06 | B7: Leads and consulting | C7: Boundary value analysis | D7: P2 | E7: A 151-character name is too long (maximum + 1) | F7: AC-25 | G7: A lead name of 151 characters is refused with "Quá dài." | I7: 1. Name of 151 characters, channel Zalo; save → "Quá dài."; nothing saved | J7: Automated | L7: PASSED | M7: PASSED
A8: LEAD-07 | B8: Leads and consulting | C8: Equivalence partitioning | D8: P1 | E8: A lead without a channel is refused | F8: AC-25 | G8: A lead needs a channel: saving with a name but no channel shows "Bắt buộc nhập." under the channel. | I8: 1. Name only; save → "Bắt buộc nhập." under Kênh liên hệ | J8: Automated | L8: PASSED | M8: PASSED
A9: LEAD-08 | B9: Leads and consulting | C9: Boundary value analysis | D9: P2 | E9: A 7-digit phone is refused (minimum − 1) | F9: BR-202 | G9: A lead phone has 8 to 15 digits: 7 digits show "Số điện thoại không hợp lệ." | I9: 1. Phone 0912345, channel Zalo; save → "Số điện thoại không hợp lệ." | J9: Automated | L9: PASSED | M9: PASSED
A10: LEAD-09 | B10: Leads and consulting | C10: Boundary value analysis | D10: P2 | E10: An 8-digit phone is accepted (minimum) | F10: BR-202 | G10: A lead phone of 8 digits is accepted. | I10: 1. Phone 09123456; save without a channel → No phone error | J10: Automated | L10: PASSED | M10: PASSED
A11: LEAD-10 | B11: Leads and consulting | C11: Boundary value analysis | D11: P2 | E11: A 15-digit phone is accepted (maximum) | F11: BR-202 | G11: A lead phone of 15 digits is accepted. | I11: 1. Phone 091234567890123; save without a channel → No phone error | J11: Automated | L11: PASSED | M11: PASSED
A12: LEAD-11 | B12: Leads and consulting | C12: Boundary value analysis | D12: P2 | E12: A 16-digit phone is refused (maximum + 1) | F12: BR-202 | G12: A lead phone of 16 digits shows "Số điện thoại không hợp lệ." | I12: 1. Phone 0912345678901234; save → "Số điện thoại không hợp lệ." | J12: Automated | L12: PASSED | M12: PASSED
A13: LEAD-12 | B13: Leads and consulting | C13: Equivalence partitioning | D13: P2 | E13: A phone with letters is refused | F13: BR-202 | G13: A lead phone containing letters shows "Số điện thoại không hợp lệ." | I13: 1. Phone 09abc45678; save → "Số điện thoại không hợp lệ." | J13: Automated | L13: PASSED | M13: PASSED
A14: LEAD-13 | B14: Leads and consulting | C14: Equivalence partitioning | D14: P3 | E14: A phone typed with spaces is accepted | F14: BR-202 | G14: A lead phone typed with spaces, e.g. "0912 345 678", is normalized and accepted. | I14: 1. Phone "0912 345 678"; save without a channel → No phone error | J14: Automated | L14: PASSED | M14: PASSED
... A18: LEAD-17 | B18: Leads and consulting | C18: Decision table | D18: P3 | E18: Another channel needs no note | F18: AC-04 | G18: A channel other than "Khác" shows no "Ghi rõ" field and saves without a note. | I18: 1. Channel Zalo; look for "Ghi rõ" → No "Ghi rõ" field 2. Save → Saved | J18: Automated | L18: PASSED | M18: PASSED
A19: LEAD-18 | B19: Leads and consulting | C19: Equivalence partitioning | D19: P1 | E19: A phone of an existing customer offers a merge | F19: BR-202 | G19: A new lead with a customer's phone (0909123456, KH000001 Nguyễn Văn An) opens "Số điện thoại đã có hồ sơ" naming that record and offering "Gộp vào hồ sơ này". | H19: Customer KH000001 Nguyễn Văn An, phone 0909123456 | I19: 1. Add a lead with phone 0909123456; save → The duplicate dialog names KH000001 · Nguyễn Văn An and offers the merge | J19: Automated | L19: PASSED | M19: PASSED
A20: LEAD-19 | B20: Leads and consulting | C20: Equivalence partitioning | D20: P1 | E20: A phone of an existing lead offers a merge | F20: BR-202 | G20: A new lead with another lead's phone (0901234508, Tạ Thu Uyên) opens "Số điện thoại đã có hồ sơ" naming that lead. | H20: Lead Tạ Thu Uyên, phone 0901234508 | I20: 1. Add a lead with phone 0901234508; save → The duplicate dialog names Tạ Thu Uyên | J20: Automated | L20: PASSED | M20: PASSED
A21: LEAD-20 | B21: Leads and consulting | C21: Use case | D21: P2 | E21: "Quay lại sửa" returns to the form with the values kept | F21: BR-202 | G21: In the duplicate dialog, "Quay lại sửa" closes it and keeps the lead form open for editing. | I21: 1. Trigger the duplicate dialog; choose "Quay lại sửa" → The dialog closes; "Thêm lead" is still open | J21: Automated | L21: PASSED | M21: PASSED
A22: LEAD-21 | B22: Leads and consulting | C22: Use case | D22: P1 | E22: "Gộp vào hồ sơ này" adds the inquiry to the existing record and creates none | F22: BR-202 | G22: Merging adds the new inquiry (channel, source, need, note) to the existing record and leaves one record. | I22: 1. Trigger the duplicate dialog; choose the merge → The existing record's timeline shows the inquiry 2. Count records with that phone → Still one | J22: Manual | K22: Changes shared business data (money, merges, deletions); kept manual until a scoped approval and cleanup exist for it.
A23: LEAD-22 | B23: Leads and consulting | C23: Use case | D23: P2 | E23: A manager merges two existing records of one person | F23: FR-LEAD-009 | G23: A manager merges two records of one person; one record remains with both histories. | I23: 1. Merge two leads of the same person → One record with both histories 2. Try merging two customers → "Chưa thể gộp hai hồ sơ khách hàng." | J23: Manual | K23: Changes shared business data (money, merges, deletions); kept manual until a scoped approval and cleanup exist for it.
A24: LEAD-23 | B24: Leads and consulting | C24: Equivalence partitioning | D24: P2 | E24: Search by phone finds only the matching lead | F24: FR-LEAD-006 | G24: Searching leads for 0901234508 lists "Tạ Thu Uyên" and not "Kiều Quốc Việt". | I24: 1. Search 0901234508 → Only Tạ Thu Uyên | J24: Automated | L24: PASSED | M24: PASSED
A25: LEAD-24 | B25: Leads and consulting | C25: Equivalence partitioning | D25: P2 | E25: Search by name finds the lead | F25: FR-LEAD-006 | G25: Searching leads for "Kiều Quốc Việt" lists that lead. | I25: 1. Search "Kiều Quốc Việt" → Kiều Quốc Việt is listed | J25: Automated | L25: PASSED | M25: PASSED
A26: LEAD-25 | B26: Leads and consulting | C26: Equivalence partitioning | D26: P3 | E26: A search with no match says so | F26: FR-LEAD-006 | G26: A lead search with no match shows "Không tìm thấy lead". | I26: 1. Search "zz-no-such-lead" → "Không tìm thấy lead" | J26: Automated | L26: PASSED | M26: PASSED
A27: LEAD-26 | B27: Leads and consulting | C27: Error guessing | D27: P2 | E27: A search that looks like SQL is treated as text | F27: FR-LEAD-006 | G27: Searching for "' OR 1=1 --" is treated as plain text and shows "Không tìm thấy lead". | I27: 1. Search "' OR 1=1 --" → "Không tìm thấy lead"; no error page | J27: Automated | L27: PASSED | M27: PASSED
A28: LEAD-27 | B28: Leads and consulting | C28: Error guessing | D28: P2 | E28: A name with HTML is shown as text | F28: FR-LEAD-002 | G28: A lead named "<b>QA LEAD-27</b>" is shown with the literal text, not as markup. | I28: 1. Save a lead named "<b>QA LEAD-27</b>" → The heading shows the angle brackets as typed | J28: Automated | L28: PASSED | M28: PASSED
A29: LEAD-28 | B29: Leads and consulting | C29: Error guessing | D29: P3 | E29: A name with control characters is refused | F29: FR-LEAD-002 | G29: A lead name with control characters shows "Có ký tự không hợp lệ." | I29: 1. Paste a name containing a control character; save → "Có ký tự không hợp lệ." | J29: Manual | K29: Needs human judgement (layout, phone usability, wording).
A30: LEAD-29 | B30: Leads and consulting | C30: Error guessing | D30: P2 | E30: Double-clicking Save creates one lead | F30: FR-LEAD-001 | G30: Submitting the quick form twice quickly creates one lead. | I30: 1. Double-click "Lưu" → One new lead | J30: Manual | K30: Needs two simultaneous requests; the executor runs one browser session at a time.
A31: LEAD-30 | B31: Leads and consulting | C31: Use case | D31: P3 | E31: The Kanban board has a column per status | F31: FR-LEAD-006 | G31: The lead Kanban board shows the columns "Mới", "Đang tư vấn" and "Từ chối". | I31: 1. Leads > Kanban → Columns Mới, Đang tư vấn, Từ chối, … | J31: Automated | L31: PASSED | M31: PASSED
A32: LEAD-31 | B32: Leads and consulting | C32: Use case | D32: P2 | E32: A new lead is assigned to a consultant | F32: BR-203 | G32: A new lead is assigned to an active consultant of the branch ("Người phụ trách" is set, not "Chưa phân công"). | I32: 1. Save a new lead → Its page shows a consultant in charge | J32: Automated | L32: PASSED | M32: PASSED
A33: LEAD-32 | B33: Leads and consulting | C33: Use case | D33: P1 | E33: Leads are shared by turn weight among receiving consultants | F33: AC-26 | G33: Leads are shared by turn weight; each move is in the history. | H33: A branch with two receiving consultants, weights 2 and 1 | I33: 1. Add three leads → Shared 2:1 in turn order; history shows each assignment | J33: Manual | K33: Needs data the demo seed does not have; prepared by hand or by an API fixture first.
A34: LEAD-33 | B34: Leads and consulting | C34: Boundary value analysis | D34: P1 | E34: An untouched lead moves on after 1 working hour, never outside 08:30–20:30 | F34: AC-26 | G34: A lead not taken care of after 1 working hour moves on, never outside 08:30–20:30. | I34: 1. Leave a lead untouched 59 working minutes → Not moved 2. 60 working minutes → Moved to the next consultant 3. At 20:29 leave it → Clock pauses until 08:30 | J34: Manual | K34: Depends on time passing (timers, reminders, expiry); needs a controllable clock.
A35: LEAD-34 | B35: Leads and consulting | C35: State transition | D35: P1 | E35: Only the moves allowed from the current status are offered | F35: BR-204 | G35: From "Mới" only the allowed moves are offered; each move is recorded. | I35: 1. Open a "Mới" lead > "Đổi trạng thái" → Only the allowed next statuses 2. Move to "Đang tư vấn" → Recorded in the history | J35: Manual | K35: Changes shared business data (money, merges, deletions); kept manual until a scoped approval and cleanup exist for it.
A36: LEAD-35 | B36: Leads and consulting | C36: State transition | D36: P1 | E36: Refused needs a reason and sends the lead to re-care in 15 days | F36: BR-204 | G36: Refused requires a reason; the lead enters re-care with a contact-again date 15 days later and is never closed. | I36: 1. Set "Từ chối" without a reason → Refused 2. With a reason → In re-care, contact-again date today + 15 | J36: Manual | K36: Expected values depend on today's date; needs date-relative inputs and assertions in the executor.
A37: LEAD-36 | B37: Leads and consulting | C37: State transition | D37: P2 | E37: No response and No show also go to re-care | F37: BR-204 | G37: No response and No show leads enter the re-care queue with a contact-again date. | I37: 1. Set "Chưa phản hồi" → In re-care 2. Set "No show" → In re-care | J37: Manual | K37: Expected values depend on today's date; needs date-relative inputs and assertions in the executor.
A38: LEAD-37 | B38: Leads and consulting | C38: Decision table | D38: P1 | E38: Converting at Show needs ID document, birth date, nationality and email | F38: BR-206 | G38: Converting to a customer requires ID card or passport, birth date, nationality and email; the record keeps its ID. | I38: 1. Show with each field missing in turn → Conversion refused, naming the missing field 2. All present → Converted; same record ID | J38: Manual | K38: Changes shared business data (money, merges, deletions); kept manual until a scoped approval and cleanup exist for it.
A39: LEAD-38 | B39: Leads and consulting | C39: State transition | D39: P2 | E39: A ticked checklist step cannot be unticked except by Admin with a reason | F39: AC-27 | G39: A ticked checklist step cannot be unticked; Admin removes a tick with a reason. | I39: 1. Consultant: tick a step, try to untick → No way to untick 2. Admin removes it with a reason → The step opens again | J39: Manual | K39: Needs two people acting in sequence (submit, then approve as someone else) inside one test.
A40: LEAD-39 | B40: Leads and consulting | C40: Boundary value analysis | D40: P2 | E40: An overdue step locks after its grace period | F40: AC-27 | G40: An overdue step past its grace period locks as "Không thực hiện" and cannot be ticked late. | I40: 1. Tick just inside the grace period → Ticked, marked late 2. After the grace period → Locked "Không thực hiện" | J40: Manual | K40: Depends on time passing (timers, reminders, expiry); needs a controllable clock.
A41: LEAD-40 | B41: Leads and consulting | C41: Use case | D41: P2 | E41: Reminder steps are created at the right times | F41: AC-07 | G41: Reminder steps at 60 minutes, 24 hours, 3 hours and 60 minutes before the visit, and 15 days are created at the right time. | I41: 1. Book an appointment → Each reminder step exists with its due time | J41: Manual | K41: Depends on time passing (timers, reminders, expiry); needs a controllable clock.
A42: LEAD-41 | B42: Leads and consulting | C42: Use case | D42: P2 | E42: "Today's tasks" lists due and overdue steps | F42: FR-LEAD-005 | G42: "Today's tasks" per consultant shows due and overdue steps. | I42: 1. Open "Việc hôm nay" as a consultant → Due and overdue steps, overdue highlighted | J42: Manual | K42: Depends on time passing (timers, reminders, expiry); needs a controllable clock.
A43: LEAD-42 | B43: Leads and consulting | C43: Use case | D43: P2 | E43: A manager reassigns a lead | F43: BR-203 | G43: Managers may reassign a lead; the move is in the history and both consultants are told. | I43: 1. Reassign a lead → New person in charge; history and notifications | J43: Manual | K43: Changes shared business data (money, merges, deletions); kept manual until a scoped approval and cleanup exist for it.
A44: LEAD-43 | B44: Leads and consulting | C44: Use case | D44: P3 | E44: The script library answers in Vietnamese and English with copy | F44: FR-LEAD-010 | G44: Script library: situations with Vietnamese and English answers and a copy button, managed by managers. | I44: 1. Open a script; copy the English answer → Copied text matches | J44: Manual | K44: Needs human judgement (layout, phone usability, wording).

Sheet Customers & contracts
A1: ID | B1: Section | C1: Technique | D1: Priority | E1: Title | F1: Requirement ID | G1: Requirement | H1: Preconditions | I1: Steps (action → expected) | J1: Type | K1: Why manual | L1: Agent run 1 | M1: Agent run 2 | N1: Observed on failure | O1: Tester result | P1: Tester notes | Q1: Tested on
A2: CUS-01 | B2: Customers | C2: Equivalence partitioning | D2: P2 | E2: Customer standing "Đang tập" (a contract running) | F2: BR-207 | G2: Customer status is derived from contracts: Lê Minh Tuấn (a contract running) shows "Đang tập" in the customer list. | H2: Lê Minh Tuấn in the demo data: a contract running | I2: 1. Open Customers → Lê Minh Tuấn's row shows "Đang tập" | J2: Automated | L2: PASSED | M2: PASSED
A3: CUS-02 | B3: Customers | C3: Equivalence partitioning | D3: P2 | E3: Customer standing "Sắp hết hạn" (the longest contract ends in exactly 30 days) | F3: BR-207 | G3: Customer status is derived from contracts: Đinh Công Sơn (the longest contract ends in exactly 30 days) shows "Sắp hết hạn" in the customer list. | H3: Đinh Công Sơn in the demo data: the longest contract ends in exactly 30 days | I3: 1. Open Customers → Đinh Công Sơn's row shows "Sắp hết hạn" | J3: Automated | L3: PASSED | M3: PASSED
A4: CUS-03 | B4: Customers | C4: Equivalence partitioning | D4: P2 | E4: Customer standing "Hết hạn" (every contract has ended) | F4: BR-207 | G4: Customer status is derived from contracts: Ngô Gia Bảo (every contract has ended) shows "Hết hạn" in the customer list. | H4: Ngô Gia Bảo in the demo data: every contract has ended | I4: 1. Open Customers → Ngô Gia Bảo's row shows "Hết hạn" | J4: Automated | L4: PASSED | M4: PASSED
A5: CUS-04 | B5: Customers | C5: Equivalence partitioning | D5: P2 | E5: Customer standing "Chưa có hợp đồng" (the only contract was cancelled) | F5: BR-207 | G5: Customer status is derived from contracts: Phan Thị Kim Ngân (the only contract was cancelled) shows "Chưa có hợp đồng" in the customer list. | H5: Phan Thị Kim Ngân in the demo data: the only contract was cancelled | I5: 1. Open Customers → Phan Thị Kim Ngân's row shows "Chưa có hợp đồng" | J5: Automated | L5: PASSED | M5: PASSED
A6: CUS-05 | B6: Customers | C6: Equivalence partitioning | D6: P2 | E6: Customer standing "Ngừng hoạt động" (customer set inactive) | F6: BR-207 | G6: Customer status is derived from contracts: Lý Thị Hoa (customer set inactive) shows "Ngừng hoạt động" in the customer list. | H6: Lý Thị Hoa in the demo data: customer set inactive | I6: 1. Open Customers → Lý Thị Hoa's row shows "Ngừng hoạt động" | J6: Automated | L6: PASSED | M6: PASSED
A7: CUS-06 | B7: Customers | C7: Boundary value analysis | D7: P2 | E7: Expiring soon starts at 30 days before the end | F7: BR-207 | G7: A customer is "Sắp hết hạn" when the contract that runs longest ends within 30 days (A-131): 31 days left is "Đang tập". | I7: 1. Contract ending in 31 days → "Đang tập" 2. Ending in 30 days → "Sắp hết hạn" 3. Ended yesterday → "Hết hạn" | J7: Manual | K7: Expected values depend on today's date; needs date-relative inputs and assertions in the executor.
A8: CUS-07 | B8: Customers | C8: Equivalence partitioning | D8: P2 | E8: Search customers by phone | F8: FR-CUS-003 | G8: Searching customers for 0966554433 lists Ngô Gia Bảo and not Lê Minh Tuấn. | I8: 1. Search 0966554433 → Only Ngô Gia Bảo | J8: Automated | L8: PASSED | M8: PASSED
A9: CUS-08 | B9: Customers | C9: Equivalence partitioning | D9: P3 | E9: Search customers by code | F9: FR-CUS-003 | G9: Searching customers for code KH000008 lists Ngô Gia Bảo. | I9: 1. Search KH000008 → Ngô Gia Bảo | J9: Automated | L9: PASSED | M9: PASSED
A10: CUS-09 | B10: Customers | C10: Equivalence partitioning | D10: P3 | E10: A customer search with no match says so | F10: FR-CUS-003 | G10: A customer search with no match shows "Không có kết quả". | I10: 1. Search "zz-no-such-customer" → "Không có kết quả" | J10: Automated | L10: PASSED | M10: PASSED
A11: CUS-10 | B11: Customers | C11: Use case | D11: P2 | E11: The customer profile has all its tabs | F11: FR-CUS-004 | G11: A customer page has the tabs Thông tin, Hợp đồng, Lịch tập, Thanh toán, Lịch sử tư vấn, Giáo án and Email đã gửi. | I11: 1. Open Lý Thị Hoa → All seven tabs | J11: Automated | L11: PASSED | M11: PASSED
A12: CUS-11 | B12: Customers | C12: Boundary value analysis | D12: P1 | E12: A customer phone is required with 8 to 15 digits | F12: FR-CUS-001 | G12: A customer phone is required, 8 to 15 digits: empty and 7 digits are refused, 8 and 15 accepted, 16 refused. | I12: 1. Add a customer with each phone value → Empty/7/16 refused; 8/15 accepted | J12: Manual | K12: Changes shared business data (money, merges, deletions); kept manual until a scoped approval and cleanup exist for it.
A13: CUS-12 | B13: Customers | C13: Equivalence partitioning | D13: P2 | E13: A customer email is required and must be valid | F13: FR-CUS-001 | G13: A customer email is required: empty shows "Bắt buộc nhập.", malformed shows "Email không hợp lệ." | I13: 1. Save without email → "Bắt buộc nhập." 2. Save "an@" → "Email không hợp lệ." | J13: Manual | K13: Changes shared business data (money, merges, deletions); kept manual until a scoped approval and cleanup exist for it.
A14: CUS-13 | B14: Customers | C14: Use case | D14: P2 | E14: Customers without email are highlighted for reception | F14: FR-CUS-005 | G14: Customers without email are highlighted for reception. | I14: 1. Open Customers as reception → Rows without email stand out | J14: Manual | K14: Needs human judgement (layout, phone usability, wording).
A15: CUS-14 | B15: Customers | C15: Decision table | D15: P1 | E15: Changing a customer's identity needs the manager's approval | F15: BR-103 | G15: Editing a customer's identity (name, phone, email, documents) takes effect only after approval by the Fitness Manager. | I15: 1. Reception changes the phone → Pending; old phone still shown 2. Manager approves → New phone shown | J15: Manual | K15: Needs two people acting in sequence (submit, then approve as someone else) inside one test.
A16: CUS-15 | B16: Customers | C16: Error guessing | D16: P1 | E16: ID numbers and health notes are encrypted and served only through signed links | F16: D-042 | G16: ID numbers and health notes are encrypted at rest; files are served only through signed links. | I16: 1. Read the database row → Ciphertext 2. Open a document link after it expires → Refused | J16: Manual | K16: Needs human judgement (layout, phone usability, wording).
A17: CUS-16 | B17: Customers | C17: Permission matrix | D17: P2 | E17: A trainer sees only their own customers | F17: BR-101 | G17: A PT (data scope own) sees only their own customers. | I17: 1. Open Customers as the trainer → Only customers the trainer coaches | J17: Manual | K17: Needs data the demo seed does not have; prepared by hand or by an API fixture first.
A18: CON-01 | B18: Contracts | C18: Boundary value analysis | D18: P1 | E18: 1 session(s) price from the tier: 500.000 ₫ | F18: AC-10 | G18: Entering 1 sessions of PT (tier 500.000 ₫ per session) gives the name "PT 1 buổi" and the total 500.000 ₫. | H18: Signed in as the manager; customer Phan Thị Kim Ngân has no running contract | I18: 1. New contract, service PT, 1 sessions → The price panel shows "PT 1 buổi" and 500.000 ₫; nothing is saved | J18: Automated | L18: PASSED | M18: PASSED
A19: CON-02 | B19: Contracts | C19: Equivalence partitioning | D19: P1 | E19: 24 session(s) price from the tier: 12.000.000 ₫ | F19: AC-10 | G19: Entering 24 sessions of PT (tier 500.000 ₫ per session) gives the name "PT 24 buổi" and the total 12.000.000 ₫. | H19: Signed in as the manager; customer Phan Thị Kim Ngân has no running contract | I19: 1. New contract, service PT, 24 sessions → The price panel shows "PT 24 buổi" and 12.000.000 ₫; nothing is saved | J19: Automated | L19: PASSED | M19: PASSED
A20: CON-03 | B20: Contracts | C20: Boundary value analysis | D20: P1 | E20: 1000 session(s) price from the tier: 500.000.000 ₫ | F20: AC-10 | G20: Entering 1000 sessions of PT (tier 500.000 ₫ per session) gives the name "PT 1000 buổi" and the total 500.000.000 ₫. | H20: Signed in as the manager; customer Phan Thị Kim Ngân has no running contract | I20: 1. New contract, service PT, 1000 sessions → The price panel shows "PT 1000 buổi" and 500.000.000 ₫; nothing is saved | J20: Automated | L20: PASSED | M20: PASSED
A21: CON-04 | B21: Contracts | C21: Boundary value analysis | D21: P1 | E21: Submitting zero sessions is refused | F21: AC-10 | G21: Submitting a contract with zero sessions ("0") shows "Nhập một số nguyên từ 1 đến 1000." and creates nothing. | I21: 1. New contract, PT, sessions "0"; "Tạo hợp đồng" → "Nhập một số nguyên từ 1 đến 1000."; still on the form | J21: Automated | L21: PASSED | M21: PASSED
A22: CON-05 | B22: Contracts | C22: Boundary value analysis | D22: P1 | E22: Submitting too many (1001) sessions is refused | F22: AC-10 | G22: Submitting a contract with too many (1001) sessions ("1001") shows "Nhập một số nguyên từ 1 đến 1000." and creates nothing. | I22: 1. New contract, PT, sessions "1001"; "Tạo hợp đồng" → "Nhập một số nguyên từ 1 đến 1000."; still on the form | J22: Automated | L22: PASSED | M22: PASSED
A23: CON-06 | B23: Contracts | C23: Equivalence partitioning | D23: P1 | E23: Submitting non-numeric sessions is refused | F23: AC-10 | G23: Submitting a contract with non-numeric sessions ("abc") shows "Nhập một số nguyên từ 1 đến 1000." and creates nothing. | I23: 1. New contract, PT, sessions "abc"; "Tạo hợp đồng" → "Nhập một số nguyên từ 1 đến 1000."; still on the form | J23: Automated | L23: PASSED | M23: PASSED
A24: CON-07 | B24: Contracts | C24: Boundary value analysis | D24: P3 | E24: The live price for 1001 sessions explains the range in Vietnamese | F24: AC-10 | G24: Before saving, typing 1001 sessions shows the range message "Nhập một số nguyên từ 1 đến 1000." in the price panel, as the form does on save. | I24: 1. Type 1001 sessions; leave the field → The price panel says "Nhập một số nguyên từ 1 đến 1000." | J24: Automated | L24: FAILED | M24: FAILED | N24: range-message: expected "Nhập một số nguyên từ 1 đến 1000", observed "Giá hợp đồng Too big: expected number to be <=1000"
A25: CON-08 | B25: Contracts | C25: Boundary value analysis | D25: P1 | E25: The end date is the start plus the tier's validity | F25: BR-301 | G25: A contract's end date is computed from the tier: PT 24 sessions ends 181 days after the start. | I25: 1. 24 sessions starting today → End date = today + 181 days | J25: Manual | K25: Expected values depend on today's date; needs date-relative inputs and assertions in the executor.
A26: CON-09 | B26: Contracts | C26: Decision table | D26: P1 | E26: A price off the tier is an exception price needing a reason and approval | F26: BR-302 | G26: A price different from the tier is an exception price: reason required, approval required, both prices stored. | I26: 1. "Giá ngoại lệ" without a reason → Refused 2. With a reason → Flagged; cannot be activated until approved | J26: Manual | K26: Needs two people acting in sequence (submit, then approve as someone else) inside one test.
A27: CON-10 | B27: Contracts | C27: Decision table | D27: P2 | E27: Promotion, then voucher, then VAT | F27: BR-303 | G27: Promotions and vouchers apply to the tier price (promotion first, voucher on the rest, then VAT) and are not exception prices. | I27: 1. Choose a 10% promotion and a 100.000 voucher, VAT 8% → Total = ((tier × 0.9) − 100.000) × 1.08 | J27: Manual | K27: Needs arithmetic across several displayed values; the executor compares text and does not compute.
A28: CON-11 | B28: Contracts | C28: Boundary value analysis | D28: P2 | E28: PT and Sale shares each total 100% | F28: BR-308 | G28: PT and Sale shares on a contract each total 100%: 99% and 101% are refused. | I28: 1. Sale shares 60% + 39% → Refused 2. 60% + 40% → Accepted 3. 60% + 41% → Refused | J28: Manual | K28: Changes shared business data (money, merges, deletions); kept manual until a scoped approval and cleanup exist for it.
A29: CON-12 | B29: Contracts | C29: State transition | D29: P1 | E29: An approved contract has no Edit action | F29: BR-305 | G29: An approved contract "Đang hiệu lực" is never edited: its page has no "Sửa hợp đồng". | H29: HD000007 approved and active | I29: 1. Open HD000007 → "Đang hiệu lực"; no "Sửa hợp đồng" | J29: Automated | L29: PASSED | M29: PASSED
A30: CON-13 | B30: Contracts | C30: State transition | D30: P1 | E30: An expired contract shows "Hết hạn" | F30: BR-402 | G30: Contract HD000009 ended 10 days ago and shows "Hết hạn". | I30: 1. Open HD000009 → "Hết hạn" | J30: Automated | L30: PASSED | M30: PASSED
A31: CON-14 | B31: Contracts | C31: State transition | D31: P2 | E31: A cancelled contract shows "Đã hủy" | F31: BR-304 | G31: Contract HD000010 (Phan Thị Kim Ngân) was cancelled and shows "Đã hủy". | I31: 1. Open HD000010 → "Đã hủy" | J31: Automated | L31: PASSED | M31: PASSED
A32: CON-15 | B32: Contracts | C32: Equivalence partitioning | D32: P1 | E32: Sessions left and debt are derived | F32: BR-602 | G32: HD000007 (24 sessions, 3 completed, no receipts) shows "Còn lại" 21 and "Còn nợ" 12.000.000 ₫. | I32: 1. Open HD000007 → Còn lại 21; Còn nợ 12.000.000 ₫ | J32: Automated | L32: PASSED | M32: PASSED
A33: CON-16 | B33: Contracts | C33: Use case | D33: P3 | E33: The contract page has its three tabs | F33: FR-CON-005 | G33: A contract page has the tabs "Thông tin", "Lịch sử check-in" and "Lịch sử gói tập". | I33: 1. Open HD000007 → Three tabs | J33: Automated | L33: PASSED | M33: PASSED
A34: CON-17 | B34: Contracts | C34: Permission matrix | D34: P1 | E34: A receptionist sees a contract but cannot cancel it | F34: AC-01 | G34: A receptionist sees contracts but cannot cancel them: HD000007 shows no "Hủy hợp đồng". | I34: 1. Open HD000007 as the receptionist → Shown; no "Hủy hợp đồng" | J34: Automated | L34: PASSED | M34: PASSED
A35: CON-18 | B35: Contracts | C35: Permission matrix | D35: P1 | E35: A receptionist cannot create a contract | F35: AC-01 | G35: A receptionist (no contract create) sees a customer's contracts but no "Thêm hợp đồng". | I35: 1. Open Phan Thị Kim Ngân > Hợp đồng as the receptionist → HD000010 listed; no "Thêm hợp đồng" | J35: Automated | L35: PASSED | M35: PASSED
A36: CON-19 | B36: Contracts | C36: State transition | D36: P1 | E36: A new contract waits for approval; its creator cannot approve it | F36: BR-304 | G36: A contract is created "Chờ duyệt" and can be edited only while pending; nobody approves their own. | I36: 1. Create a contract → "Chờ duyệt"; editable 2. Approve it as its creator → "Bạn không thể tự duyệt yêu cầu do chính mình gửi." 3. Approve as another manager → "Đang hiệu lực"; no longer editable | J36: Manual | K36: Needs two people acting in sequence (submit, then approve as someone else) inside one test.
A37: CON-20 | B37: Contracts | C37: State transition | D37: P2 | E37: A rejected contract has no effect | F37: BR-304 | G37: A contract the approver rejects is "Đã từ chối" and has no effect; a rejection needs a reason. | I37: 1. Reject without a reason → Refused 2. With a reason → "Đã từ chối"; cannot be booked or paid | J37: Manual | K37: Needs two people acting in sequence (submit, then approve as someone else) inside one test.
A38: CON-21 | B38: Contracts | C38: Decision table | D38: P2 | E38: Unapproving is allowed only with no receipts or sessions | F38: BR-304 | G38: An approved contract can be sent back to pending only with no receipts or sessions. | I38: 1. Unapprove with a receipt → Refused 2. Without receipts or sessions → Back to "Chờ duyệt" | J38: Manual | K38: Changes shared business data (money, merges, deletions); kept manual until a scoped approval and cleanup exist for it.
A39: CON-22 | B39: Contracts | C39: Decision table | D39: P1 | E39: Deleting a contract with receipts is blocked and lists them | F39: AC-12 | G39: Deleting a contract with receipts is blocked and the receipts to delete first are listed; after deleting in order, totals fall by exactly those amounts. | I39: 1. Delete a contract with receipts → Blocked, receipts listed 2. Delete receipts, then the contract → Revenue and receipts fall by the deleted amounts; both in the trash | J39: Manual | K39: Changes shared business data (money, merges, deletions); kept manual until a scoped approval and cleanup exist for it.
A40: CON-23 | B40: Contracts | C40: State transition | D40: P1 | E40: Freezing and reactivating extend the end date once | F40: AC-14 | G40: A frozen contract cannot be booked or checked in; reactivation shows the frozen days and proposed end date; it changes only after admin confirms and never twice. | I40: 1. Deactivate with a reason → "Tạm vô hiệu"; booking refused 2. Reactivate after 10 days → Proposed end date + 10 days; confirmed once 3. Freeze and reactivate again → No second extension | J40: Manual | K40: Depends on time passing (timers, reminders, expiry); needs a controllable clock.
A41: CON-24 | B41: Contracts | C41: Boundary value analysis | D41: P2 | E41: A freeze longer than 10 days reminds the manager | F41: BR-307 | G41: A freeze longer than 10 days creates a reminder task. | I41: 1. Frozen for 10 days → No reminder 2. 11 days → Reminder task | J41: Manual | K41: Depends on time passing (timers, reminders, expiry); needs a controllable clock.
A42: CON-25 | B42: Contracts | C42: State transition | D42: P2 | E42: A renewal voucher waits for approval and then adds sessions | F42: FR-CHG-002 | G42: An approved renewal voucher updates the derived figures; before approval it has no effect. | I42: 1. Raise a renewal → Pending; figures unchanged 2. Approve → Sessions and end date updated | J42: Manual | K42: Needs two people acting in sequence (submit, then approve as someone else) inside one test.
A43: CON-26 | B43: Contracts | C43: State transition | D43: P2 | E43: A transfer moves the remaining sessions to the receiver | F43: FR-CHG-001 | G43: A transfer needs a receiver; once approved the giver has no sessions left and the receiver has them. | I43: 1. Raise a transfer without a receiver → Refused 2. With a receiver; approve → Sessions moved | J43: Manual | K43: Needs two people acting in sequence (submit, then approve as someone else) inside one test.
A44: CON-27 | B44: Contracts | C44: Decision table | D44: P2 | E44: A cancellation with refund creates the expense voucher | F44: FR-CHG-002 | G44: An approved cancellation creates the refund expense voucher. | I44: 1. Raise a cancellation with refund → Needs reason, payment method, expense type 2. Approve → Contract "Đã hủy"; refund voucher in the cash book | J44: Manual | K44: Changes shared business data (money, merges, deletions); kept manual until a scoped approval and cleanup exist for it.
A45: CON-28 | B45: Contracts | C45: Use case | D45: P2 | E45: The contract list totals what the filter matches | F45: FR-CON-004 | G45: The contract list totals value, paid and debt for the filter. | I45: 1. Filter by payment status "Chưa thanh toán" → Totals equal the sum of the listed rows | J45: Manual | K45: Needs arithmetic across several displayed values; the executor compares text and does not compute.
A46: CON-29 | B46: Contracts | C46: Use case | D46: P3 | E46: Imported contracts keep their opening balances | F46: BR-309 | G46: Opening balances of imported contracts are set once and never edited. | I46: 1. Open HD000011 (imported) → Opening sessions used and paid amount shown; no way to edit them | J46: Manual | K46: Needs human judgement (layout, phone usability, wording).

Sheet Booking & sessions
A1: ID | B1: Section | C1: Technique | D1: Priority | E1: Title | F1: Requirement ID | G1: Requirement | H1: Preconditions | I1: Steps (action → expected) | J1: Type | K1: Why manual | L1: Agent run 1 | M1: Agent run 2 | N1: Observed on failure | O1: Tester result | P1: Tester notes | Q1: Tested on
A2: BKG-01 | B2: PT booking | C2: Decision table | D2: P1 | E2: A booking on an eligible contract is created | F2: BR-402 | G2: A booking on an approved, active contract with sessions left, within its dates and the service hours, is created. | H2: An active contract with sessions left | I2: 1. Book a free cell within the contract dates → The session appears in the PT's column | J2: Manual | K2: Expected values depend on today's date; needs date-relative inputs and assertions in the executor.
A3: BKG-02 | B3: PT booking | C3: Decision table | D3: P1 | E3: A contract not yet approved cannot be booked | F3: BR-402 | G3: A booking requires an approved, active contract with sessions left, not expired and not frozen, inside the service's hours: a contract still "Chờ duyệt" is refused with "Hợp đồng không ở trạng thái hiệu lực (đang nháp, đã hủy hoặc đã hết hạn)." | H3: a contract still "Chờ duyệt" | I3: 1. PT calendar: book a session on it → Refused: "Hợp đồng không ở trạng thái hiệu lực (đang nháp, đã hủy hoặc đã hết hạn)."; no session created | J3: Manual | K3: Expected values depend on today's date; needs date-relative inputs and assertions in the executor.
A4: BKG-03 | B4: PT booking | C4: Decision table | D4: P1 | E4: An expired contract cannot be booked | F4: BR-402 | G4: A booking requires an approved, active contract with sessions left, not expired and not frozen, inside the service's hours: an expired contract (HD000009) is refused with "Hợp đồng không ở trạng thái hiệu lực (đang nháp, đã hủy hoặc đã hết hạn)." | H4: an expired contract (HD000009) | I4: 1. PT calendar: book a session on it → Refused: "Hợp đồng không ở trạng thái hiệu lực (đang nháp, đã hủy hoặc đã hết hạn)."; no session created | J4: Manual | K4: Expected values depend on today's date; needs date-relative inputs and assertions in the executor.
A5: BKG-04 | B5: PT booking | C5: Decision table | D5: P1 | E5: A cancelled contract cannot be booked | F5: BR-402 | G5: A booking requires an approved, active contract with sessions left, not expired and not frozen, inside the service's hours: a cancelled contract (HD000010) is refused with "Hợp đồng không ở trạng thái hiệu lực (đang nháp, đã hủy hoặc đã hết hạn)." | H5: a cancelled contract (HD000010) | I5: 1. PT calendar: book a session on it → Refused: "Hợp đồng không ở trạng thái hiệu lực (đang nháp, đã hủy hoặc đã hết hạn)."; no session created | J5: Manual | K5: Expected values depend on today's date; needs date-relative inputs and assertions in the executor.
A6: BKG-05 | B6: PT booking | C6: Decision table | D6: P1 | E6: A frozen contract cannot be booked | F6: BR-402 | G6: A booking requires an approved, active contract with sessions left, not expired and not frozen, inside the service's hours: a contract "Tạm vô hiệu" is refused with "Hợp đồng đang bị khóa. Hãy kích hoạt lại trước." | H6: a contract "Tạm vô hiệu" | I6: 1. PT calendar: book a session on it → Refused: "Hợp đồng đang bị khóa. Hãy kích hoạt lại trước."; no session created | J6: Manual | K6: Expected values depend on today's date; needs date-relative inputs and assertions in the executor.
A7: BKG-06 | B7: PT booking | C7: Decision table | D7: P1 | E7: A contract with no sessions left cannot be booked | F7: BR-402 | G7: A booking requires an approved, active contract with sessions left, not expired and not frozen, inside the service's hours: a contract with 0 sessions left is refused with "Hợp đồng không còn buổi tập nào khả dụng." | H7: a contract with 0 sessions left | I7: 1. PT calendar: book a session on it → Refused: "Hợp đồng không còn buổi tập nào khả dụng."; no session created | J7: Manual | K7: Expected values depend on today's date; needs date-relative inputs and assertions in the executor.
A8: BKG-07 | B8: PT booking | C8: Decision table | D8: P2 | E8: A date outside the contract period is refused | F8: BR-402 | G8: A booking requires an approved, active contract with sessions left, not expired and not frozen, inside the service's hours: a date after the contract's end date is refused with "Ngày tập nằm ngoài thời hạn của hợp đồng." | H8: a date after the contract's end date | I8: 1. PT calendar: book a session on it → Refused: "Ngày tập nằm ngoài thời hạn của hợp đồng."; no session created | J8: Manual | K8: Expected values depend on today's date; needs date-relative inputs and assertions in the executor.
A9: BKG-08 | B9: PT booking | C9: Decision table | D9: P2 | E9: A time outside the service hours is refused | F9: BR-402 | G9: A booking requires an approved, active contract with sessions left, not expired and not frozen, inside the service's hours: a time outside the service's allowed hours is refused with "Giờ này nằm ngoài khung giờ được dùng dịch vụ." | H9: a time outside the service's allowed hours | I9: 1. PT calendar: book a session on it → Refused: "Giờ này nằm ngoài khung giờ được dùng dịch vụ."; no session created | J9: Manual | K9: Expected values depend on today's date; needs date-relative inputs and assertions in the executor.
A10: BKG-09 | B10: PT booking | C10: Decision table | D10: P2 | E10: A booking over the daily limit is refused | F10: BR-402 | G10: A booking requires an approved, active contract with sessions left, not expired and not frozen, inside the service's hours: a second session in a day for a service limited to one per day is refused with "Dịch vụ không cho thêm buổi nào cho khách trong ngày này." | H10: a second session in a day for a service limited to one per day | I10: 1. PT calendar: book a session on it → Refused: "Dịch vụ không cho thêm buổi nào cho khách trong ngày này."; no session created | J10: Manual | K10: Expected values depend on today's date; needs date-relative inputs and assertions in the executor.
A11: BKG-10 | B11: PT booking | C11: Equivalence partitioning | D11: P1 | E11: A trainer cannot have two sessions at once | F11: BR-403 | G11: A PT cannot have two sessions at once: "Huấn luyện viên đã có lịch trùng giờ này." | H11: Trainer Khoa has a session at 17:00 today | I11: 1. Book another customer with Khoa at 17:00 → "Huấn luyện viên đã có lịch trùng giờ này." | J11: Manual | K11: Expected values depend on today's date; needs date-relative inputs and assertions in the executor.
A12: BKG-11 | B12: PT booking | C12: Equivalence partitioning | D12: P1 | E12: A customer cannot have two sessions at once | F12: BR-403 | G12: A customer cannot have two sessions at once: "Khách đã có buổi tập khác vào giờ này." | I12: 1. Book the same customer with another PT at an overlapping time → "Khách đã có buổi tập khác vào giờ này." | J12: Manual | K12: Expected values depend on today's date; needs date-relative inputs and assertions in the executor.
A13: BKG-12 | B13: PT booking | C13: Boundary value analysis | D13: P2 | E13: Back-to-back sessions do not overlap | F13: BR-403 | G13: A session ending at 18:00 and another starting at 18:00 for the same PT do not overlap. | I13: 1. Book 17:00–18:00 and 18:00–19:00 for one PT → Both created 2. Book 17:30–18:30 → Refused as an overlap | J13: Manual | K13: Expected values depend on today's date; needs date-relative inputs and assertions in the executor.
A14: BKG-13 | B14: PT booking | C14: Boundary value analysis | D14: P2 | E14: An end time not after the start is explained before saving | F14: FR-PT-002 | G14: An end time not after the start shows "Giờ kết thúc phải sau giờ bắt đầu." before anything is saved. | I14: 1. End 17:00, start 17:00 → "Giờ kết thúc phải sau giờ bắt đầu." 2. End 16:30 → Same message | J14: Manual | K14: Expected values depend on today's date; needs date-relative inputs and assertions in the executor.
A15: BKG-14 | B15: PT booking | C15: Boundary value analysis | D15: P2 | E15: Times must be on the hour or half hour | F15: FR-PT-001 | G15: Times are 30-minute cells: 05:15 shows "Chọn giờ tròn hoặc giờ rưỡi, ví dụ 05:00 hoặc 05:30." | I15: 1. Start 05:15 → Refused with the half-hour message 2. 05:30 → Accepted | J15: Manual | K15: Expected values depend on today's date; needs date-relative inputs and assertions in the executor.
A16: BKG-15 | B16: PT booking | C16: Use case | D16: P2 | E16: A PT can book outside the on-duty shift | F16: AC-24 | G16: A PT can book outside the on-duty shift, and the grid colors in-shift and off-shift time differently. | I16: 1. Book an off-shift cell → Created 2. Look at the grid → Off-shift cells shaded differently | J16: Manual | K16: Needs human judgement (layout, phone usability, wording).
A17: BKG-16 | B17: PT booking | C17: Error guessing | D17: P1 | E17: Two concurrent bookings of the same slot create one | F17: BR-403 | G17: Overlaps are refused even under concurrent requests (enforced by the database). | I17: 1. Two users book the same trainer slot at the same moment → One succeeds, one is refused | J17: Manual | K17: Needs two simultaneous requests; the executor runs one browser session at a time.
A18: BKG-17 | B18: PT booking | C18: Permission matrix | D18: P2 | E18: A trainer sees only their own column | F18: BR-101 | G18: A PT with data scope own sees and completes only their own sessions. | I18: 1. Open the PT calendar as a trainer → Only their column | J18: Manual | K18: Needs data the demo seed does not have; prepared by hand or by an API fixture first.
A19: BKG-18 | B19: PT booking | C19: Use case | D19: P3 | E19: Reception opens the PT calendar | F19: FR-PT-001 | G19: Reception opens the PT calendar "Lịch PT". | I19: 1. Open Lịch PT as the receptionist → The calendar opens | J19: Automated | L19: PASSED | M19: PASSED
A20: SES-01 | B20: Sessions | C20: State transition | D20: P1 | E20: Booking never consumes a session | F20: BR-401 | G20: Booking never consumes a session. | I20: 1. Note sessions left; book → Unchanged | J20: Manual | K20: Needs a record created earlier in the same test, with its new id carried to later steps; the executor cannot do that yet.
A21: SES-02 | B21: Sessions | C21: Decision table | D21: P1 | E21: "Đã tập" consumes one session and credits the PT | F21: BR-404 | G21: "Đã tập" consumes a session and credits the PT. | I21: 1. Mark a booked session "Đã tập" → Sessions left −1; PT credited 1 | J21: Manual | K21: Needs a record created earlier in the same test, with its new id carried to later steps; the executor cannot do that yet.
A22: SES-03 | B22: Sessions | C22: Decision table | D22: P1 | E22: "Khách không đến" consumes one session and credits the PT | F22: BR-404 | G22: "Khách không đến" consumes a session and credits the PT. | I22: 1. Mark "Khách không đến" → Sessions left −1; PT credited | J22: Manual | K22: Needs a record created earlier in the same test, with its new id carried to later steps; the executor cannot do that yet.
A23: SES-04 | B23: Sessions | C23: Decision table | D23: P1 | E23: "Hủy lịch" neither consumes nor credits | F23: BR-404 | G23: "Hủy lịch" does not consume or credit. | I23: 1. Cancel a booked session → Sessions left unchanged; no credit | J23: Manual | K23: Needs a record created earlier in the same test, with its new id carried to later steps; the executor cannot do that yet.
A24: SES-05 | B24: Sessions | C24: State transition | D24: P1 | E24: "Đã tập" is final | F24: BR-405 | G24: "Đã tập" requires its own permission and is final: its status cannot change. | I24: 1. Try to change a "Đã tập" session → No status actions offered | J24: Manual | K24: Needs a record created earlier in the same test, with its new id carried to later steps; the executor cannot do that yet.
A25: SES-06 | B25: Sessions | C25: Error guessing | D25: P1 | E25: Repeating a status change never consumes twice | F25: BR-409 | G25: Repeating a status change never consumes twice, also under concurrent requests. | I25: 1. Send "Đã tập" twice → Sessions left −1 only | J25: Manual | K25: Needs two simultaneous requests; the executor runs one browser session at a time.
A26: SES-07 | B26: Sessions | C26: Use case | D26: P1 | E26: Deleting a recorded session refunds exactly one and emails the customer | F26: AC-16 | G26: When admin deletes a "Đã tập" session, the customer gets exactly 1 session back and the PT exactly 1 credit less. | I26: 1. Delete from the check-in history with a reason → +1 session; −1 PT credit; one email; in the trash | J26: Manual | K26: Changes shared business data (money, merges, deletions); kept manual until a scoped approval and cleanup exist for it.
A27: SES-08 | B27: Sessions | C27: Use case | D27: P2 | E27: Deleting a session in a paid period adds an adjustment | F27: BR-407 | G27: Deleting a session in a period already paid to the PT keeps the payout and adds a negative adjustment to the next period. | I27: 1. Delete a session from a paid period → Next period shows a −1 adjustment line | J27: Manual | K27: Changes shared business data (money, merges, deletions); kept manual until a scoped approval and cleanup exist for it.
A28: SES-09 | B28: Sessions | C28: Use case | D28: P2 | E28: Burn Show needs a reason and counts like "Đã tập" | F28: BR-408 | G28: Burn Show adds a session by hand with a mandatory reason; it consumes and credits like Đã tập and is marked "added by hand". | I28: 1. Burn Show without a reason → Refused 2. With a reason → Session added by hand; −1 left; PT credited | J28: Manual | K28: Changes shared business data (money, merges, deletions); kept manual until a scoped approval and cleanup exist for it.
A29: SES-10 | B29: Sessions | C29: Use case | D29: P2 | E29: Admin confirms a day's sessions in bulk | F29: FR-PT-004 | G29: Admin confirms many sessions of a day quickly ("Đã tập" in bulk). | I29: 1. Select several checked-in sessions; confirm → All "Đã tập"; each consumed once | J29: Manual | K29: Changes shared business data (money, merges, deletions); kept manual until a scoped approval and cleanup exist for it.
A30: SES-11 | B30: Sessions | C30: Use case | D30: P2 | E30: Each session status shows its configured color | F30: AC-15 | G30: Each session status shows its color. | I30: 1. Look at the calendar → Colors match the status rules | J30: Manual | K30: Needs human judgement (layout, phone usability, wording).
A31: CLS-01 | B31: Classes and check-in | C31: Boundary value analysis | D31: P1 | E31: A full class refuses another enrolment | F31: BR-411 | G31: Class enrollment is refused when the class is full: "Lớp đã đầy." | I31: 1. Class capacity 10 with 9 enrolled: enroll one → Enrolled 2. Enroll the 11th → "Lớp đã đầy." | J31: Manual | K31: Needs data the demo seed does not have; prepared by hand or by an API fixture first.
... A37: CHK-03 | B37: Classes and check-in | C37: Use case | D37: P2 | E37: A session without a full check-in is chased | F37: AC-30 | G37: A session without a full check-in is notified to its PT at the end of the day, and to the Studio Manager with a task after 24 hours. | I37: 1. Leave a session half checked-in → PT told at day end; manager task after 24 h | J37: Manual | K37: Depends on time passing (timers, reminders, expiry); needs a controllable clock.

Sheet Operations
A1: ID | B1: Section | C1: Technique | D1: Priority | E1: Title | F1: Requirement ID | G1: Requirement | H1: Preconditions | I1: Steps (action → expected) | J1: Type | K1: Why manual | L1: Agent run 1 | M1: Agent run 2 | N1: Observed on failure | O1: Tester result | P1: Tester notes | Q1: Tested on
A2: MON-01 | B2: Money | C2: Boundary value analysis | D2: P1 | E2: A receipt of 0 is refused | F2: BR-603 | G2: Receipt amounts are greater than zero: 0 shows "Số tiền phải lớn hơn 0." | I2: 1. Record a payment of 0 → "Số tiền phải lớn hơn 0." | J2: Manual | K2: Changes shared business data (money, merges, deletions); kept manual until a scoped approval and cleanup exist for it.
A3: MON-02 | B3: Money | C3: Boundary value analysis | D3: P1 | E3: A receipt of 1 ₫ is accepted | F3: BR-603 | G3: A receipt of 1 ₫ is accepted. | I3: 1. Record 1 → Recorded, pending approval | J3: Manual | K3: Changes shared business data (money, merges, deletions); kept manual until a scoped approval and cleanup exist for it.
A4: MON-03 | B4: Money | C4: Boundary value analysis | D4: P1 | E4: A receipt equal to the debt is accepted | F4: BR-604 | G4: A receipt may take the paid amount up to the contract value: paying exactly the debt is accepted. | I4: 1. HD000007 owes 12.000.000: record 12.000.000 → Accepted; debt 0 once approved | J4: Manual | K4: Changes shared business data (money, merges, deletions); kept manual until a scoped approval and cleanup exist for it.
A5: MON-04 | B5: Money | C5: Boundary value analysis | D5: P1 | E5: A receipt above the debt is refused | F5: BR-604 | G5: A receipt may not take the paid amount above the contract value: "Khoản thanh toán làm tổng đã trả vượt giá trị hợp đồng." | I5: 1. Record 12.000.001 on HD000007 → "Khoản thanh toán làm tổng đã trả vượt giá trị hợp đồng." | J5: Manual | K5: Changes shared business data (money, merges, deletions); kept manual until a scoped approval and cleanup exist for it.
A6: MON-05 | B6: Money | C6: Equivalence partitioning | D6: P2 | E6: A non-integer amount is refused | F6: BR-603 | G6: Amounts are whole đồng: "1.5" shows "Số tiền không hợp lệ. Nhập số đồng nguyên, ví dụ 12.000.000." | I6: 1. Amount 1.5 → Invalid amount message | J6: Manual | K6: Changes shared business data (money, merges, deletions); kept manual until a scoped approval and cleanup exist for it.
A7: MON-06 | B7: Money | C7: Equivalence partitioning | D7: P1 | E7: A payment on a cancelled contract is refused | F7: BR-601 | G7: A payment on a cancelled contract is refused: "Không ghi nhận thanh toán cho hợp đồng đã hủy." | I7: 1. Pay on HD000010 → "Không ghi nhận thanh toán cho hợp đồng đã hủy." | J7: Manual | K7: Changes shared business data (money, merges, deletions); kept manual until a scoped approval and cleanup exist for it.
A8: MON-07 | B8: Money | C8: Decision table | D8: P1 | E8: Paid and debt count only approved, undeleted receipts | F8: BR-602 | G8: Paid amount, debt and payment status are computed only from valid receipts (approved, not deleted) plus the opening paid amount. | I8: 1. Add a pending receipt → Debt unchanged 2. Approve it → Debt falls by the amount 3. Delete it → Debt back | J8: Manual | K8: Needs two people acting in sequence (submit, then approve as someone else) inside one test.
A9: MON-08 | B9: Money | C9: Use case | D9: P1 | E9: Paid and debt always equal the receipts | F9: AC-19 | G9: Each contract's paid amount and debt always equal the sum of its valid receipts. | I9: 1. Two approved receipts 5.000.000 and 3.000.000 on a 12.000.000 contract → Paid 8.000.000; debt 4.000.000 | J9: Manual | K9: Needs arithmetic across several displayed values; the executor compares text and does not compute.
A10: MON-09 | B10: Money | C10: Use case | D10: P1 | E10: The cash book balances | F10: AC-19 | G10: Cash book closing balance equals opening balance plus receipts minus expenses. | I10: 1. Open Sổ quỹ for a day and method → Closing = opening + in − out | J10: Manual | K10: Needs arithmetic across several displayed values; the executor compares text and does not compute.
A11: MON-10 | B11: Money | C11: Permission matrix | D11: P2 | E11: Only Admin edits a receipt date, and it is logged | F11: BR-605 | G11: Editing a receipt's date is a separate permission (Admin) and is always logged. | I11: 1. Manager opens a receipt → No date edit 2. Admin edits the date → Saved; action history shows before and after | J11: Manual | K11: Needs two people acting in sequence (submit, then approve as someone else) inside one test.
A12: MON-11 | B12: Money | C12: Use case | D12: P2 | E12: Deleting a receipt asks for a reason and returns the amount to the debt | F12: BR-104 | G12: Deleting a receipt requires a reason, waits for an admin, moves it to the trash and puts the amount back into the debt. | I12: 1. Delete a receipt with "Khác" and no note → Refused 2. With a reason; admin approves → In the trash; debt restored | J12: Manual | K12: Changes shared business data (money, merges, deletions); kept manual until a scoped approval and cleanup exist for it.
A13: MON-12 | B13: Money | C13: Error guessing | D13: P1 | E13: A PT payout never pays a session twice | F13: AC-18 | G13: PT payout vouchers never pay a session twice. | I13: 1. Pay a period → One voucher 2. Pay the same period again → "Không còn gì để chi cho PT trong kỳ này…" | J13: Manual | K13: Changes shared business data (money, merges, deletions); kept manual until a scoped approval and cleanup exist for it.
A14: MON-13 | B14: Money | C14: Boundary value analysis | D14: P2 | E14: An expense voucher must be greater than zero | F14: BR-603 | G14: Expense amounts are greater than zero. | I14: 1. Expense of 0 → "Số tiền phải lớn hơn 0." 2. 1 → Accepted | J14: Not drafted | K14: Changes shared business data (money, merges, deletions); kept manual until a scoped approval and cleanup exist for it.
A15: MON-14 | B15: Money | C15: Permission matrix | D15: P2 | E15: A receptionist has payments and debt but not income and expenses | F15: AC-01 | G15: A receptionist opens Finance and sees the tabs "Thanh toán" and "Công nợ" but not "Thu / Chi". | I15: 1. Open Finance as the receptionist → "Thanh toán" and "Công nợ"; no "Thu / Chi" | J15: Automated | L15: PASSED | M15: PASSED
A16: MON-15 | B16: Money | C16: Permission matrix | D16: P3 | E16: A manager has income and expenses | F16: AC-01 | G16: A Fitness Manager sees the Finance tab "Thu / Chi". | I16: 1. Open Finance as the manager → "Thu / Chi" is there | J16: Automated | L16: PASSED | M16: PASSED
A17: APR-01 | B17: Approvals, trash and audit | C17: Decision table | D17: P1 | E17: The submitter cannot approve their own request | F17: AC-05 | G17: Actions in approval groups have no effect until approved; the submitter cannot approve them: "Bạn không thể tự duyệt yêu cầu do chính mình gửi." | I17: 1. Submit a receipt as the manager; approve it yourself → Refused 2. Another approver approves → Takes effect | J17: Manual | K17: Needs two people acting in sequence (submit, then approve as someone else) inside one test.
A18: APR-02 | B18: Approvals, trash and audit | C18: State transition | D18: P1 | E18: A pending request has no effect | F18: BR-103 | G18: Actions configured in the approval matrix take effect only after approval. | I18: 1. Submit; check the figures before approval → Unchanged | J18: Manual | K18: Needs two people acting in sequence (submit, then approve as someone else) inside one test.
A19: APR-03 | B19: Approvals, trash and audit | C19: Decision table | D19: P2 | E19: A rejection needs a reason | F19: FR-PLT-007 | G19: Rejection takes a reason. | I19: 1. Reject without a reason → Refused 2. With a reason → Rejected; reason shown to the submitter | J19: Manual | K19: Needs two people acting in sequence (submit, then approve as someone else) inside one test.
A20: APR-04 | B20: Approvals, trash and audit | C20: Boundary value analysis | D20: P2 | E20: An approval pending over 24 hours goes to the approver's manager | F20: AC-28 | G20: A slow approval past 24 hours is told to the approver's direct manager. | I20: 1. Pending 23 h 59 → No escalation 2. 24 h → Direct manager told | J20: Manual | K20: Depends on time passing (timers, reminders, expiry); needs a controllable clock.
A21: APR-05 | B21: Approvals, trash and audit | C21: Use case | D21: P2 | E21: Admin switches approval on or off per action on screen | F21: AC-05 | G21: Admin switches approval on or off and changes approvers per action type on screen; the change takes effect immediately. | I21: 1. Turn off approval for receipts → The next receipt takes effect at once | J21: Manual | K21: Needs two people acting in sequence (submit, then approve as someone else) inside one test.
A22: APR-06 | B22: Approvals, trash and audit | C22: Use case | D22: P3 | E22: Every role can open its approvals page | F22: FR-PLT-007 | G22: Deciding a request needs no permission of its own: a receptionist opens "Phê duyệt". | I22: 1. Open Phê duyệt as the receptionist → The page opens | J22: Automated | L22: PASSED | M22: PASSED
A23: TRS-01 | B23: Approvals, trash and audit | C23: Use case | D23: P1 | E23: Deleted data is in the trash with its reason and cannot be purged | F23: AC-13 | G23: Deleted data is in the trash with its reason, viewable only by management, and cannot be deleted. | I23: 1. Delete a record with a reason → In the trash with who, when and why 2. Look for purge or restore → None | J23: Manual | K23: Changes shared business data (money, merges, deletions); kept manual until a scoped approval and cleanup exist for it.
A24: TRS-02 | B24: Approvals, trash and audit | C24: Error guessing | D24: P2 | E24: Codes are never reused after a deletion | F24: BR-105 | G24: Codes are unique and never reused. | I24: 1. Delete the newest lead; add another → It gets the next code, not the deleted one | J24: Manual | K24: Changes shared business data (money, merges, deletions); kept manual until a scoped approval and cleanup exist for it.
A25: AUD-01 | B25: Approvals, trash and audit | C25: Use case | D25: P1 | E25: Every change is audited with before and after values | F25: BR-106 | G25: Every create, update, delete, approval and change of roles, permissions, thresholds or configuration is audited with before and after values. | I25: 1. Edit a lead's phone → Action history shows old and new phone, who and when | J25: Manual | K25: Needs two people acting in sequence (submit, then approve as someone else) inside one test.
A26: CFG-01 | B26: Configuration | C26: Use case | D26: P1 | E26: An option added on screen shows immediately; old data is unchanged | F26: AC-03 | G26: Admin adds or deactivates an option on screen, the change shows immediately, and old data is unchanged. | I26: 1. Add a channel option → Available in the lead form at once 2. Deactivate it → Not offered; old leads keep it | J26: Manual | K26: Needs two people acting in sequence (submit, then approve as someone else) inside one test.
A27: CFG-02 | B27: Configuration | C27: Error guessing | D27: P2 | E27: "Khác" cannot be deactivated | F27: BR-102 | G27: "Khác" is always available: deactivating it shows "Lựa chọn "Khác" luôn được dùng, không thể ngừng." | I27: 1. Deactivate "Khác" → Refused | J27: Manual | K27: Changes shared business data (money, merges, deletions); kept manual until a scoped approval and cleanup exist for it.
A28: CFG-03 | B28: Configuration | C28: Use case | D28: P2 | E28: Parameters change behaviour without a developer | F28: AC-02 | G28: Admin changes permissions, approval thresholds, price tiers, timers and session status rules on screen; changes take effect immediately. | I28: 1. Change the re-care days from 15 to 10 → The next refused lead gets +10 days | J28: Manual | K28: Expected values depend on today's date; needs date-relative inputs and assertions in the executor.
A29: CFG-04 | B29: Configuration | C29: Boundary value analysis | D29: P2 | E29: A role's discount threshold is 0 to 100 | F29: FR-PLT-002 | G29: A role's discount threshold is kept between 0 and 100; over 100 is refused. | I29: 1. Set 100 → Kept 2. Set 101 → Refused | J29: Manual | K29: Changes shared business data (money, merges, deletions); kept manual until a scoped approval and cleanup exist for it.
A30: CFG-05 | B30: Configuration | C30: Equivalence partitioning | D30: P2 | E30: Overlapping price tiers are refused | F30: FR-SVC-002 | G30: Price tiers of a service may not overlap. | I30: 1. Tiers 1–12 and 10–24 → Refused 2. 1–12 and 13–24 → Saved | J30: Manual | K30: Changes shared business data (money, merges, deletions); kept manual until a scoped approval and cleanup exist for it.
A31: CFG-06 | B31: Configuration | C31: Error guessing | D31: P2 | E31: A service name in use is refused in any case | F31: FR-SVC-001 | G31: A service name already in use, in any letter case, is refused: "Tên này đã được dùng." | I31: 1. Add service "pt" → "Tên này đã được dùng." | J31: Manual | K31: Changes shared business data (money, merges, deletions); kept manual until a scoped approval and cleanup exist for it.
A32: CFG-07 | B32: Configuration | C32: Equivalence partitioning | D32: P2 | E32: A voucher code in use is refused | F32: FR-SVC-004 | G32: A voucher code already in use is refused. | I32: 1. Add a voucher with an existing code → Refused | J32: Manual | K32: Changes shared business data (money, merges, deletions); kept manual until a scoped approval and cleanup exist for it.
A33: CFG-08 | B33: Configuration | C33: Use case | D33: P3 | E33: A price version from tomorrow does not change today's price | F33: FR-SVC-002 | G33: Price tiers have versions with effective dates; a version from tomorrow does not change today's price. | I33: 1. Save a new tier version effective tomorrow → Today's contract form shows the old price | J33: Manual | K33: Expected values depend on today's date; needs date-relative inputs and assertions in the executor.
A34: CFG-09 | B34: Configuration | C34: Permission matrix | D34: P2 | E34: Only Admin changes session status rules | F34: AC-02 | G34: Only Admin changes session status rules and colors. | I34: 1. Open Trạng thái buổi tập as the manager → Refused or read-only 2. As Admin → Editable | J34: Manual | K34: Needs two people acting in sequence (submit, then approve as someone else) inside one test.
... A38: TSK-04 | B38: Tasks and notifications | C38: Boundary value analysis | D38: P2 | E38: Reminders at 24, 3 and 1 hours before the deadline | F38: AC-28 | G38: A task is reminded at all three points before its deadline through the bell, email and phone. | I38: 1. Task due in 25 h → Reminded at 24 h, 3 h and 1 h before | J38: Manual | K38: Depends on time passing (timers, reminders, expiry); needs a controllable clock.
A39: TSK-05 | B39: Tasks and notifications | C39: Permission matrix | D39: P3 | E39: Every role has its tasks page | F39: FR-TASK-005 | G39: Tasks are for every role: a PT opens "Công việc". | I39: 1. Open Công việc as the trainer → The page opens | J39: Automated | L39: PASSED | M39: PASSED
A40: MAIL-01 | B40: Tasks and notifications | C40: Use case | D40: P1 | E40: Each credited or refunded session sends exactly one email | F40: AC-17 | G40: Every credited or refunded session sends exactly one email to the customer, from the template and in the right language, with its status stored in the profile. | I40: 1. Complete a session → One email, status on "Email đã gửi" 2. Refund it → One more email | J40: Manual | K40: Involves email, push notifications or devices outside the browser.
A41: MAIL-02 | B41: Tasks and notifications | C41: Equivalence partitioning | D41: P2 | E41: The email language follows the nationality | F41: BR-701 | G41: Emails go in the language of the customer's nationality group (Vietnamese or foreign). | I41: 1. Vietnamese customer → Vietnamese email 2. Foreign customer → English email | J41: Manual | K41: Involves email, push notifications or devices outside the browser.
A42: MAIL-03 | B42: Tasks and notifications | C42: Error guessing | D42: P2 | E42: A failed email creates a reception task | F42: FR-MAIL-003 | G42: Email failures create a reception task. | I42: 1. Make an email fail → Status failed with the reason; reception task | J42: Manual | K42: Involves email, push notifications or devices outside the browser.
A43: NTF-01 | B43: Tasks and notifications | C43: Use case | D43: P3 | E43: Users read their notifications | F43: FR-PLT-009 | G43: Users receive in-app notifications on the page "Thông báo". | I43: 1. Open Thông báo as the manager → The page opens | J43: Automated | L43: PASSED | M43: PASSED
A44: WKO-01 | B44: Workouts | C44: Use case | D44: P1 | E44: Plans and session logs show plan and actual on one row | F44: AC-20 | G44: A customer's plans and every session log are visible in their profile, with plan and actual on the same row. | I44: 1. Open a customer's Giáo án tab → Plans and logs; plan and actual side by side | J44: Manual | K44: Needs data the demo seed does not have; prepared by hand or by an API fixture first.
A45: WKO-02 | B45: Workouts | C45: Equivalence partitioning | D45: P2 | E45: A Cardio exercise shows time, speed and heart rate | F45: BR-502 | G45: Cardio rows show time, speed and heart rate instead of weights. | I45: 1. Add a Cardio exercise → Time, speed, HR columns 2. Strength exercise → Weight and reps | J45: Manual | K45: Needs data the demo seed does not have; prepared by hand or by an API fixture first.
A46: WKO-03 | B46: Workouts | C46: State transition | D46: P1 | E46: "Stop + Escalation" waits until a manager or Master handles it | F46: AC-21 | G46: Choosing Action "Stop + Escalation" notifies the manager and Master, and the item stays in the waiting list until handled. | I46: 1. Coach escalates a set → Manager and Master told; task open 2. Master marks it reviewed with a note → Removed from the waiting list | J46: Manual | K46: Needs two people acting in sequence (submit, then approve as someone else) inside one test.
A47: WKO-04 | B47: Workouts | C47: State transition | D47: P2 | E47: A plan needs Master approval | F47: BR-504 | G47: Creating and editing plans and templates needs Master approval. | I47: 1. PT sends a plan → Pending 2. Master approves → In use; edits need a new version | J47: Manual | K47: Needs two people acting in sequence (submit, then approve as someone else) inside one test.
A48: WKO-05 | B48: Workouts | C48: Use case | D48: P2 | E48: The weekly workout dashboard gives the right Flag and Action percentages | F48: AC-21 | G48: The weekly workout dashboard gives the right Flag and Action percentages. | I48: 1. Fixed dataset of sets with flags → Percentages match a hand count | J48: Manual | K48: Needs arithmetic across several displayed values; the executor compares text and does not compute.
A49: WKO-06 | B49: Workouts | C49: Use case | D49: P2 | E49: The session log works on a phone | F49: AC-23 | G49: The lead, PT calendar and session log screens work on a phone. | I49: 1. Open the log at phone width → Usable without sideways scrolling | J49: Manual | K49: Needs human judgement (layout, phone usability, wording).
A50: RPT-01 | B50: Reports | C50: Use case | D50: P1 | E50: The consulting dashboard matches the September and October files | F50: AC-08 | G50: The consulting dashboard gives the right lead counts, booking rate and show rate per consultant compared with the Excel files of September and October 2026. | I50: 1. Compare the dashboard with the files → Same counts and rates | J50: Manual | K50: Needs data the demo seed does not have; prepared by hand or by an API fixture first.
A51: RPT-02 | B51: Reports | C51: Use case | D51: P1 | E51: PT revenue allocation matches GymMaster | F51: AC-18 | G51: The PT revenue allocation report matches GymMaster's export on the same data. | I51: 1. Same period in both systems → Same totals per PT | J51: Manual | K51: Needs data the demo seed does not have; prepared by hand or by an API fixture first.
A52: RPT-03 | B52: Reports | C52: Use case | D52: P2 | E52: Lists export to Excel with the visible columns | F52: FR-RPT-001 | G52: Reports and lists export to Excel, filtered as on screen. | I52: 1. Export the contract list with a filter → The file has the same rows | J52: Manual | K52: Involves email, push notifications or devices outside the browser.
A53: RPT-04 | B53: Reports | C53: Error guessing | D53: P2 | E53: A list too long to export asks for a filter | F53: FR-RPT-001 | G53: An export that is too long shows "Danh sách quá dài để xuất. Hãy lọc bớt trước." | I53: 1. Export a very large list → The message; no file | J53: Manual | K53: Needs data the demo seed does not have; prepared by hand or by an API fixture first.
A54: RPT-05 | B54: Reports | C54: Use case | D54: P2 | E54: GymMaster import reconciles | F54: AC-22 | G54: Data imported from GymMaster matches the number of customers, contract value, paid amounts and sessions left. | I54: 1. Import the files; open the reconciliation → All metrics match | J54: Manual | K54: Needs data the demo seed does not have; prepared by hand or by an API fixture first.
A55: SEC-01 | B55: Security | C55: Error guessing | D55: P2 | E55: A record id that does not exist shows "Không tìm thấy" | F55: FR-CON-005 | G55: Opening /contracts/ with an id that does not exist shows "Không tìm thấy", not an error page. | I55: 1. Open /contracts/00000000-0000-4000-8000-000000000000 → "Không tìm thấy" | J55: Automated | L55: INCONCLUSIVE | M55: INCONCLUSIVE
A56: SEC-02 | B56: Security | C56: Error guessing | D56: P1 | E56: The API refuses a request without a session | F56: AC-01 | G56: Calling GET /api/v1/customers without signing in is refused with HTTP 401. | I56: 1. GET /api/v1/customers signed out → 401 | J56: Automated | L56: PASSED | M56: PASSED
A57: SEC-03 | B57: Security | C57: Error guessing | D57: P1 | E57: The API refuses an admin endpoint to a receptionist | F57: AC-01 | G57: A signed-in receptionist calling GET /api/v1/users (Admin only) is refused with HTTP 403. | I57: 1. Sign in as the receptionist; GET /api/v1/users → 403 | J57: Automated | L57: PASSED | M57: PASSED
A58: SEC-04 | B58: Security | C58: Error guessing | D58: P1 | E58: The API refuses lead data to a trainer | F58: AC-01 | G58: A signed-in PT calling GET /api/v1/leads (no lead permission) is refused with HTTP 403. | I58: 1. Sign in as the trainer; GET /api/v1/leads → 403 | J58: Automated | L58: PASSED | M58: PASSED
A59: SEC-05 | B59: Security | C59: Error guessing | D59: P1 | E59: The OWASP security suite passes for every endpoint | F59: 24_SECURITY_TESTING | G59: Every endpoint passes the OWASP Top 10 checks in docs/24. | I59: 1. Run the security suite → All checks pass | J59: Not drafted | K59: Needs human judgement (layout, phone usability, wording).

Sheet Traceability
A1: Requirement ID | B1: Statement (first case) | C1: Cases | D1: Agent results (run 2)
A2: 24_SECURITY_TESTING | B2: Every endpoint passes the OWASP Top 10 checks in docs/24. | C2: SEC-05 | D2: SEC-05: not drafted
A3: AC-01 | B3: A visitor who is not signed in and opens /dashboard by direct URL is sent to /login. | C3: AUTH-04, AUTH-05, RBAC-01A, RBAC-01B, RBAC-02A, RBAC-02B, RBAC-03A, RBAC-03B, RBAC-04A, RBAC-04B, RBAC-05A, RBAC-05B, RBAC-06A, RBAC-06B, RBAC-07A, RBAC-07B, RBAC-08A, RBAC-08B, RBAC-09A, RBAC-09B, RBAC-10A, RBAC-10B, RBAC-11A, RBAC-11B, RBAC-12A, RBAC-12B, RBAC-13A, RBAC-13B, RBAC-14A, RBAC-14B, RBAC-15A, RBAC-15B, RBAC-16A, RBAC-16B, RBAC-17A, RBAC-17B, RBAC-18A, RBAC-18B, RBAC-19A, RBAC-19B, RBAC-20A, RBAC-20B, RBAC-21A, RBAC-21B, RBAC-22A, RBAC-22B, RBAC-23A, RBAC-23B, RBAC-24A, RBAC-24B, RBAC-25A, RBAC-25B, RBAC-26A, RBAC-26B, RBAC-27A, RBAC-27B, RBAC-28A, RBAC-28B, RBAC-29A, RBAC-29B, RBAC-30A, RBAC-30B, RBAC-M1, RBAC-M2, RBAC-M3, RBAC-M4, RBAC-M6, CON-17, CON-18, MON-14, MON-15, SEC-02, SEC-03, SEC-04 | D3: AUTH-04: PASSED, AUTH-05: PASSED, RBAC-01A: PASSED, RBAC-01B: PASSED, RBAC-02A: PASSED, RBAC-02B: PASSED, RBAC-03A: PASSED, RBAC-03B: PASSED, RBAC-04A: PASSED, RBAC-04B: PASSED, RBAC-05A: PASSED, RBAC-05B: PASSED, RBAC-06A: PASSED, RBAC-06B: PASSED, RBAC-07A: PASSED, RBAC-07B: PASSED, RBAC-08A: PASSED, RBAC-08B: PASSED, RBAC-09A: PASSED, RBAC-09B: PASSED, RBAC-10A: PASSED, RBAC-10B: PASSED, RBAC-11A: PASSED, RBAC-11B: PASSED, RBAC-12A: PASSED, RBAC-12B: PASSED, RBAC-13A: PASSED, RBAC-13B: PASSED, RBAC-14A: PASSED, RBAC-14B: PASSED, RBAC-15A: PASSED, RBAC-15B: PASSED, RBAC-16A: PASSED, RBAC-16B: PASSED, RBAC-17A: PASSED, RBAC-17B: PASSED, RBAC-18A: PASSED, RBAC-18B: PASSED, RBAC-19A: PASSED, RBAC-19B: PASSED, RBAC-20A: PASSED, RBAC-20B: PASSED, RBAC-21A: PASSED, RBAC-21B: PASSED, RBAC-22A: PASSED, RBAC-22B: PASSED, RBAC-23A: PASSED, RBAC-23B: PASSED, RBAC-24A: PASSED, RBAC-24B: PASSED, RBAC-25A: PASSED, RBAC-25B: PASSED, RBAC-26A: PASSED, RBAC-26B: PASSED, RBAC-27A: PASSED, RBAC-27B: PASSED, RBAC-28A: PASSED, RBAC-28B: PASSED, RBAC-29A: PASSED, RBAC-29B: PASSED, RBAC-30A: PASSED, RBAC-30B: PASSED, RBAC-M1: PASSED, RBAC-M2: PASSED, RBAC-M3: PASSED, RBAC-M4: PASSED, RBAC-M6: manual, CON-17: PASSED, CON-18: PASSED, MON-14: PASSED, MON-15: PASSED, SEC-02: PASSED, SEC-03: PASSED, SEC-04: PASSED
A4: AC-02 | B4: Admin changes permissions, approval thresholds, price tiers, timers and session status rules on screen; changes take effect immediately. | C4: CFG-03, CFG-09 | D4: CFG-03: manual, CFG-09: manual
A5: AC-03 | B5: Admin adds or deactivates an option on screen, the change shows immediately, and old data is unchanged. | C5: CFG-01 | D5: CFG-01: manual
A6: AC-04 | B6: Choosing "Khác" in any drop-down cannot be saved without a note. | C6: LEAD-15, LEAD-16, LEAD-17 | D6: LEAD-15: PASSED, LEAD-16: PASSED, LEAD-17: PASSED
A7: AC-05 | B7: Actions in approval groups have no effect until approved; the submitter cannot approve them: "Bạn không thể tự duyệt yêu cầu do chính mình gửi." | C7: APR-01, APR-05 | D7: APR-01: manual, APR-05: manual
A8: AC-07 | B8: Reminder steps at 60 minutes, 24 hours, 3 hours and 60 minutes before the visit, and 15 days are created at the right time. | C8: LEAD-40 | D8: LEAD-40: manual
A9: AC-08 | B9: The consulting dashboard gives the right lead counts, booking rate and show rate per consultant compared with the Excel files of September and October 2026. | C9: RPT-01 | D9: RPT-01: manual
A10: AC-10 | B10: Entering 1 sessions of PT (tier 500.000 ₫ per session) gives the name "PT 1 buổi" and the total 500.000 ₫. | C10: CON-01, CON-02, CON-03, CON-04, CON-05, CON-06, CON-07 | D10: CON-01: PASSED, CON-02: PASSED, CON-03: PASSED, CON-04: PASSED, CON-05: PASSED, CON-06: PASSED, CON-07: FAILED
A11: AC-12 | B11: Deleting a contract with receipts is blocked and the receipts to delete first are listed; after deleting in order, totals fall by exactly those amounts. | C11: CON-22 | D11: CON-22: manual
A12: AC-13 | B12: Deleted data is in the trash with its reason, viewable only by management, and cannot be deleted. | C12: TRS-01 | D12: TRS-01: manual
... A97: FR-TASK-005 | B97: Tasks are for every role: a PT opens "Công việc". | C97: TSK-05 | D97: TSK-05: PASSED

Sheet Test design
A1: Test design artifacts: each table is the design a technique produced; the last column names the cases derived from it.
A3: Sign-in, sessions, roles and permissions: Sign-in credentials | B3: Equivalence partitioning
A4: Partition | B4: Example | C4: Expected | D4: Cases
A5: Valid email + correct password | B5: demo-manager + password | C5: Dashboard | D5: AUTH-01
A6: Valid email + wrong password | B6: demo-manager + wrong | C6: Generic message | D6: AUTH-02
A7: Unknown email | B7: nobody@… | C7: Same generic message | D7: AUTH-03
A8: Disabled account | B8: disabled user | C8: Same generic message | D8: AUTH-08
A9: Outside allowed hours | B9: restricted user | C9: Refused, logged | D9: AUTH-07
A11: Sign-in, sessions, roles and permissions: Session | B11: State transition
A12: From | B12: Event | C12: To | D12: Cases
A13: Signed out | B13: Open a protected page | C13: Login page | D13: AUTH-04, AUTH-05
A14: Signed out | B14: Valid sign-in | C14: Signed in (dashboard) | D14: AUTH-01
A15: Signed in | B15: Đăng xuất | C15: Signed out | D15: AUTH-06
A16: Signed in | B16: 12 h without activity | C16: Signed out | D16: AUTH-11
A18: Sign-in, sessions, roles and permissions: Sign-in rate limit (20 per 60 s per IP) | B18: Boundary value analysis
A19: Attempt in the window | B19: Expected | C19: Case
A20: 20th | B20: Processed | C20: AUTH-10
A21: 21st | B21: HTTP 429 | C21: AUTH-10
A23: Sign-in, sessions, roles and permissions: Page access by privilege boundary (expected from docs/09_RBAC.md) | B23: Permission matrix
A24: Page | B24: Permission | C24: Allowed (least privileged) | D24: Refused (most privileged) | E24: Cases
A25: /admin/users | B25: user.manage | C25: Admin | D25: Fitness Manager | E25: RBAC-01A/B
A26: /admin/roles | B26: role.manage | C26: Admin | D26: Fitness Manager | E26: RBAC-02A/B
A27: /admin/options | B27: config.manage | C27: Admin | D27: Fitness Manager | E27: RBAC-03A/B
A28: /admin/parameters | B28: config.manage | C28: Admin | D28: Fitness Manager | E28: RBAC-04A/B
A29: /admin/trash | B29: trash.view | C29: Admin | D29: Fitness Manager | E29: RBAC-05A/B
A30: /admin/audit | B30: audit.view | C30: Admin | D30: Fitness Manager | E30: RBAC-06A/B
A31: /admin/system | B31: system.view | C31: Admin | D31: Fitness Manager | E31: RBAC-07A/B
A32: /admin/approvals | B32: approval.manage | C32: Admin | D32: Fitness Manager | E32: RBAC-08A/B
A33: /admin/email-templates | B33: mail.template | C33: Admin | D33: Fitness Manager | E33: RBAC-09A/B
A34: /admin/intake | B34: intake.manage | C34: Admin | D34: Fitness Manager | E34: RBAC-10A/B
A35: /admin/promotions | B35: config.manage | C35: Admin | D35: Receptionist | E35: RBAC-11A/B
... A54: /classes | B54: class.view | C54: Receptionist | D54: Consulting | E54: RBAC-30A/B
A56: Leads and consulting: Lead name | B56: Equivalence partitioning
A57: Partition | B57: Example | C57: Expected | D57: Case
A58: Valid (1–150) | B58: "QA LEAD-01" | C58: Saved | D58: LEAD-01, LEAD-04, LEAD-05
A59: Empty | B59: "" | C59: Bắt buộc nhập. | D59: LEAD-02
A60: Spaces only | B60: " " | C60: Bắt buộc nhập. | D60: LEAD-03
A61: Too long (>150) | B61: 151 × Q | C61: Quá dài. | D61: LEAD-06
A62: Markup | B62: <b>…</b> | C62: Shown as text | D62: LEAD-27
A63: Control characters | B63: \u0007 | C63: Có ký tự không hợp lệ. | D63: LEAD-28
A65: Leads and consulting: Lead name length (1–150) and phone digits (8–15) | B65: Boundary value analysis
A66: Field | B66: Value | C66: Expected | D66: Case
A67: Name | B67: 0 chars | C67: Bắt buộc nhập. | D67: LEAD-02
A68: Name | B68: 1 char | C68: Accepted | D68: LEAD-04
A69: Name | B69: 150 chars | C69: Accepted | D69: LEAD-05
A70: Name | B70: 151 chars | C70: Quá dài. | D70: LEAD-06
A71: Phone | B71: 7 digits | C71: Số điện thoại không hợp lệ. | D71: LEAD-08
A72: Phone | B72: 8 digits | C72: Accepted | D72: LEAD-09
A73: Phone | B73: 15 digits | C73: Accepted | D73: LEAD-10
A74: Phone | B74: 16 digits | C74: Số điện thoại không hợp lệ. | D74: LEAD-11
A76: Leads and consulting: Lead phone | B76: Equivalence partitioning
A77: Partition | B77: Example | C77: Expected | D77: Case
A78: Empty (optional) | B78: "" | C78: Saved | D78: LEAD-01
A79: Digits only | B79: 09123456 | C79: Accepted | D79: LEAD-09
A80: With spaces | B80: 0912 345 678 | C80: Normalized, accepted | D80: LEAD-13
A81: International | B81: +84912345678 | C81: Accepted | D81: LEAD-14
A82: With letters | B82: 09abc45678 | C82: Invalid | D82: LEAD-12
A83: Already a customer's | B83: 0909123456 | C83: Merge prompt | D83: LEAD-18
A84: Already a lead's | B84: 0901234508 | C84: Merge prompt | D84: LEAD-19
A86: Leads and consulting: Channel "Khác" and the note (AC-04) | B86: Decision table
A87: Channel is "Khác" | B87: Note given | C87: Expected | D87: Case
A88: Yes | B88: No | C88: Refused: Đã chọn "Khác" thì phải ghi rõ. | D88: LEAD-15
A89: Yes | B89: Yes | C89: Saved | D89: LEAD-16
A90: No | B90: — (no field) | C90: Saved | D90: LEAD-17
A91: None chosen | B91: — | C91: Bắt buộc nhập. | D91: LEAD-07
A93: Leads and consulting: Converting a lead at Show (BR-206) | B93: Decision table
A94: ID document | B94: Birth date | C94: Nationality | D94: Email | E94: Expected
A95: ✓ | B95: ✓ | C95: ✓ | D95: ✓ | E95: Converted, same ID
A96: — | B96: ✓ | C96: ✓ | D96: ✓ | E96: Refused
A97: ✓ | B97: — | C97: ✓ | D97: ✓ | E97: Refused
A98: ✓ | B98: ✓ | C98: — | D98: ✓ | E98: Refused
A99: ✓ | B99: ✓ | C99: ✓ | D99: — | E99: Refused
A101: Leads and consulting: Lead status (BR-204) | B101: State transition
A102: From | B102: Event | C102: To | D102: Cases
A103: Mới | B103: Start consulting | C103: Đang tư vấn | D103: LEAD-34
A104: Đang tư vấn | B104: Appointment | C104: Đã đặt lịch | D104: LEAD-34
A105: Đã đặt lịch | B105: Came | C105: Show → customer | D105: LEAD-37
A106: Đã đặt lịch | B106: Did not come | C106: No show → re-care | D106: LEAD-36
A107: Any open | B107: Refused + reason | C107: Từ chối → re-care +15 days | D107: LEAD-35
A108: Any open | B108: No answer | C108: Chưa phản hồi → re-care | D108: LEAD-36
A110: Customers and contracts: Customer standing (BR-207, A-131) | B110: Equivalence partitioning
A111: Partition | B111: Demo customer | C111: Expected badge | D111: Case
A112: A contract running | B112: Lê Minh Tuấn | C112: Đang tập | D112: CUS-01
A113: Ends within 30 days | B113: Đinh Công Sơn (30 days) | C113: Sắp hết hạn | D113: CUS-02
A114: All contracts ended | B114: Ngô Gia Bảo | C114: Hết hạn | D114: CUS-03
A115: No approved contract (cancelled) | B115: Phan Thị Kim Ngân | C115: Chưa có hợp đồng | D115: CUS-04
A116: Customer inactive | B116: Lý Thị Hoa | C116: Ngừng hoạt động | D116: CUS-05
A118: Customers and contracts: Sessions on a new contract (1–1000) | B118: Boundary value analysis
A119: Value | B119: Expected | C119: Case
A120: 0 | B120: Refused on save: Nhập một số nguyên từ 1 đến 1000. | C120: CON-04
A121: 1 | B121: PT 1 buổi, 500.000 ₫ | C121: CON-01
A122: 24 (typical) | B122: PT 24 buổi, 12.000.000 ₫ | C122: CON-02
A123: 1000 | B123: PT 1000 buổi, 500.000.000 ₫ | C123: CON-03
A124: 1001 | B124: Refused on save; preview explains the range | C124: CON-05, CON-07
A125: abc | B125: Refused on save | C125: CON-06
A127: Customers and contracts: Expiring soon (30 days, A-131) | B127: Boundary value analysis
A128: Days to the end | B128: Expected | C128: Case
A129: 31 | B129: Đang tập | C129: CUS-06
A130: 30 | B130: Sắp hết hạn | C130: CUS-02, CUS-06
A131: −1 | B131: Hết hạn | C131: CUS-06
...
